{
	"__comment": "Designed by Dablakbandit with Cubik Studio - https://cubik.studio",
	"textures": {
		"0": "custom/diamond_sword/construction/oak_plank",
		"1_1": "custom/diamond_pickaxe/steel_bar"
	},
	"elements": [ 	 
		{
			"__comment": "Element",
			"from": [ -2.6711, 3.0436, -4 ],
			"to": [ 3.17626, 4.05518, -3 ],
			"rotation": { "origin": [ 8, 8.17174, -3.49882 ], "axis": "z", "angle": 45 },
			"faces": {
				"down": { "uv": [ 6, 13.5, 6.5, 14 ], "texture": "#0", "cullface": "down" },
				"up": { "uv": [ 6, 13.5, 6.5, 14 ], "texture": "#0", "cullface": "up" },
				"north": { "uv": [ 4, 13.5, 4.5, 14 ], "texture": "#0", "cullface": "north" },
				"south": { "uv": [ 4, 13.5, 4.5, 14 ], "texture": "#0", "cullface": "south" },
				"west": { "uv": [ 6, 13.5, 6.5, 14 ], "texture": "#0", "cullface": "west" },
				"east": { "uv": [ 6, 13.5, 6.5, 14 ], "texture": "#0", "cullface": "east" }
			}
		},
		{
			"__comment": "Element",
			"from": [ -2.6711, 3.0436, 19 ],
			"to": [ 3.17626, 4.05518, 20 ],
			"rotation": { "origin": [ 8, 8.17174, 19.50118 ], "axis": "z", "angle": 45 },
			"faces": {
				"down": { "uv": [ 6, 13.5, 6.5, 14 ], "texture": "#0", "cullface": "down" },
				"up": { "uv": [ 6, 13.5, 6.5, 14 ], "texture": "#0", "cullface": "up" },
				"north": { "uv": [ 4, 13.5, 4.5, 14 ], "texture": "#0", "cullface": "north" },
				"south": { "uv": [ 4, 13.5, 4.5, 14 ], "texture": "#0", "cullface": "south" },
				"west": { "uv": [ 6, 13.5, 6.5, 14 ], "texture": "#0", "cullface": "west" },
				"east": { "uv": [ 6, 13.5, 6.5, 14 ], "texture": "#0", "cullface": "east" }
			}
		},
		{
			"__comment": "Element",
			"from": [ 7.5, 1.85, -4 ],
			"to": [ 8.5, 19, -3 ],
			"faces": {
				"down": { "uv": [ 6, 13.5, 6.5, 14 ], "texture": "#0", "cullface": "down" },
				"up": { "uv": [ 6, 13.5, 6.5, 14 ], "texture": "#0", "cullface": "up" },
				"north": { "uv": [ 6, 13.5, 6.5, 14 ], "texture": "#0", "cullface": "north" },
				"south": { "uv": [ 6, 13.5, 6.5, 14 ], "texture": "#0", "cullface": "south" },
				"west": { "uv": [ 6, 13.5, 6.5, 14 ], "texture": "#0", "cullface": "west" },
				"east": { "uv": [ 6, 13.5, 6.5, 14 ], "texture": "#0", "cullface": "east" }
			}
		},
		{
			"__comment": "Element",
			"from": [ 7.5, 1.85, 19 ],
			"to": [ 8.5, 19, 20 ],
			"faces": {
				"down": { "uv": [ 6, 13.5, 6.5, 14 ], "texture": "#0", "cullface": "down" },
				"up": { "uv": [ 6, 13.5, 6.5, 14 ], "texture": "#0", "cullface": "up" },
				"north": { "uv": [ 6, 13.5, 6.5, 14 ], "texture": "#0", "cullface": "north" },
				"south": { "uv": [ 6, 13.5, 6.5, 14 ], "texture": "#0", "cullface": "south" },
				"west": { "uv": [ 6, 13.5, 6.5, 14 ], "texture": "#0", "cullface": "west" },
				"east": { "uv": [ 6, 13.5, 6.5, 14 ], "texture": "#0", "cullface": "east" }
			}
		},
		{
			"__comment": "Element",
			"from": [ 3.3735, -3, -4 ],
			"to": [ 4.0806, -2.29289, -3 ],
			"faces": {
				"down": { "uv": [ 4, 13.5, 4.5, 14 ], "texture": "#0", "cullface": "down" },
				"up": { "uv": [ 4, 13.5, 4.5, 14 ], "texture": "#0", "cullface": "up" },
				"north": { "uv": [ 4, 13.5, 4.5, 14 ], "texture": "#0", "cullface": "north" },
				"south": { "uv": [ 4, 13.5, 4.5, 14 ], "texture": "#0", "cullface": "south" },
				"west": { "uv": [ 4, 13.5, 4.5, 14 ], "texture": "#0", "cullface": "west" },
				"east": { "uv": [ 4, 13.5, 4.5, 14 ], "texture": "#0", "cullface": "east" }
			}
		},
		{
			"__comment": "Element",
			"from": [ 3.3735, -3, 19 ],
			"to": [ 4.0806, -2.29289, 20 ],
			"faces": {
				"down": { "uv": [ 4, 13.5, 4.5, 14 ], "texture": "#0", "cullface": "down" },
				"up": { "uv": [ 4, 13.5, 4.5, 14 ], "texture": "#0", "cullface": "up" },
				"north": { "uv": [ 4, 13.5, 4.5, 14 ], "texture": "#0", "cullface": "north" },
				"south": { "uv": [ 4, 13.5, 4.5, 14 ], "texture": "#0", "cullface": "south" },
				"west": { "uv": [ 4, 13.5, 4.5, 14 ], "texture": "#0", "cullface": "west" },
				"east": { "uv": [ 4, 13.5, 4.5, 14 ], "texture": "#0", "cullface": "east" }
			}
		},
		{
			"__comment": "Element",
			"from": [ 12.8237, 3.0436, -4 ],
			"to": [ 18.67106, 4.05518, -3 ],
			"rotation": { "origin": [ 8, 8.17174, -3.49882 ], "axis": "z", "angle": -45 },
			"faces": {
				"down": { "uv": [ 6, 13.5, 6.5, 14 ], "texture": "#0", "cullface": "down" },
				"up": { "uv": [ 6, 13.5, 6.5, 14 ], "texture": "#0", "cullface": "up" },
				"north": { "uv": [ 4, 13.5, 4.5, 14 ], "texture": "#0", "cullface": "north" },
				"south": { "uv": [ 4, 13.5, 4.5, 14 ], "texture": "#0", "cullface": "south" },
				"west": { "uv": [ 6, 13.5, 6.5, 14 ], "texture": "#0", "cullface": "west" },
				"east": { "uv": [ 6, 13.5, 6.5, 14 ], "texture": "#0", "cullface": "east" }
			}
		},
		{
			"__comment": "Element",
			"from": [ 12.8237, 3.0436, 19 ],
			"to": [ 18.67106, 4.05518, 20 ],
			"rotation": { "origin": [ 8, 8.17174, 19.50118 ], "axis": "z", "angle": -45 },
			"faces": {
				"down": { "uv": [ 6, 13.5, 6.5, 14 ], "texture": "#0", "cullface": "down" },
				"up": { "uv": [ 6, 13.5, 6.5, 14 ], "texture": "#0", "cullface": "up" },
				"north": { "uv": [ 4, 13.5, 4.5, 14 ], "texture": "#0", "cullface": "north" },
				"south": { "uv": [ 4, 13.5, 4.5, 14 ], "texture": "#0", "cullface": "south" },
				"west": { "uv": [ 6, 13.5, 6.5, 14 ], "texture": "#0", "cullface": "west" },
				"east": { "uv": [ 6, 13.5, 6.5, 14 ], "texture": "#0", "cullface": "east" }
			}
		},
		{
			"__comment": "Element",
			"from": [ 11.9194, -3, -4 ],
			"to": [ 12.6265, -2.29289, -3 ],
			"faces": {
				"down": { "uv": [ 4, 13.5, 4.5, 14 ], "texture": "#0", "cullface": "down" },
				"up": { "uv": [ 4, 13.5, 4.5, 14 ], "texture": "#0", "cullface": "up" },
				"north": { "uv": [ 4, 13.5, 4.5, 14 ], "texture": "#0", "cullface": "north" },
				"south": { "uv": [ 4, 13.5, 4.5, 14 ], "texture": "#0", "cullface": "south" },
				"west": { "uv": [ 4, 13.5, 4.5, 14 ], "texture": "#0", "cullface": "west" },
				"east": { "uv": [ 4, 13.5, 4.5, 14 ], "texture": "#0", "cullface": "east" }
			}
		},
		{
			"__comment": "Element",
			"from": [ 11.9194, -3, 19 ],
			"to": [ 12.6265, -2.29289, 20 ],
			"faces": {
				"down": { "uv": [ 4, 13.5, 4.5, 14 ], "texture": "#0", "cullface": "down" },
				"up": { "uv": [ 4, 13.5, 4.5, 14 ], "texture": "#0", "cullface": "up" },
				"north": { "uv": [ 4, 13.5, 4.5, 14 ], "texture": "#0", "cullface": "north" },
				"south": { "uv": [ 4, 13.5, 4.5, 14 ], "texture": "#0", "cullface": "south" },
				"west": { "uv": [ 4, 13.5, 4.5, 14 ], "texture": "#0", "cullface": "west" },
				"east": { "uv": [ 4, 13.5, 4.5, 14 ], "texture": "#0", "cullface": "east" }
			}
		},
		{
			"__comment": "Element",
			"from": [ 7.5, 3.0444, -14.2207 ],
			"to": [ 8.5, 4.05598, -8.323339 ],
			"rotation": { "origin": [ 8, 8.17174, -3.49882 ], "axis": "x", "angle": -45 },
			"faces": {
				"down": { "uv": [ 6, 13.5, 6.5, 14 ], "texture": "#0", "cullface": "down" },
				"up": { "uv": [ 6, 13.5, 6.5, 14 ], "texture": "#0", "cullface": "up" },
				"north": { "uv": [ 6, 13.5, 6.5, 14 ], "texture": "#0", "cullface": "north" },
				"south": { "uv": [ 6, 13.5, 6.5, 14 ], "texture": "#0", "cullface": "south" },
				"west": { "uv": [ 4, 13.5, 4.5, 14 ], "texture": "#0", "cullface": "west" },
				"east": { "uv": [ 4, 13.5, 4.5, 14 ], "texture": "#0", "cullface": "east" }
			}
		},
		{
			"__comment": "Element",
			"from": [ 7.5, 3.0444, 8.7793 ],
			"to": [ 8.5, 4.05598, 14.67666 ],
			"rotation": { "origin": [ 8, 8.17174, 19.50118 ], "axis": "x", "angle": -45 },
			"faces": {
				"down": { "uv": [ 6, 13.5, 6.5, 14 ], "texture": "#0", "cullface": "down" },
				"up": { "uv": [ 6, 13.5, 6.5, 14 ], "texture": "#0", "cullface": "up" },
				"north": { "uv": [ 6, 13.5, 6.5, 14 ], "texture": "#0", "cullface": "north" },
				"south": { "uv": [ 6, 13.5, 6.5, 14 ], "texture": "#0", "cullface": "south" },
				"west": { "uv": [ 4, 13.5, 4.5, 14 ], "texture": "#0", "cullface": "west" },
				"east": { "uv": [ 4, 13.5, 4.5, 14 ], "texture": "#0", "cullface": "east" }
			}
		},
		{
			"__comment": "Element",
			"from": [ 7.5, -3, -8.1265 ],
			"to": [ 8.5, -2.29289, -7.4194 ],
			"faces": {
				"down": { "uv": [ 4, 13.5, 4.5, 14 ], "texture": "#0", "cullface": "down" },
				"up": { "uv": [ 4, 13.5, 4.5, 14 ], "texture": "#0", "cullface": "up" },
				"north": { "uv": [ 4, 13.5, 4.5, 14 ], "texture": "#0", "cullface": "north" },
				"south": { "uv": [ 4, 13.5, 4.5, 14 ], "texture": "#0", "cullface": "south" },
				"west": { "uv": [ 4, 13.5, 4.5, 14 ], "texture": "#0", "cullface": "west" },
				"east": { "uv": [ 4, 13.5, 4.5, 14 ], "texture": "#0", "cullface": "east" }
			}
		},
		{
			"__comment": "Element",
			"from": [ 7.5, -3, 14.8735 ],
			"to": [ 8.5, -2.29289, 15.5806 ],
			"faces": {
				"down": { "uv": [ 4, 13.5, 4.5, 14 ], "texture": "#0", "cullface": "down" },
				"up": { "uv": [ 4, 13.5, 4.5, 14 ], "texture": "#0", "cullface": "up" },
				"north": { "uv": [ 4, 13.5, 4.5, 14 ], "texture": "#0", "cullface": "north" },
				"south": { "uv": [ 4, 13.5, 4.5, 14 ], "texture": "#0", "cullface": "south" },
				"west": { "uv": [ 4, 13.5, 4.5, 14 ], "texture": "#0", "cullface": "west" },
				"east": { "uv": [ 4, 13.5, 4.5, 14 ], "texture": "#0", "cullface": "east" }
			}
		},
		{
			"__comment": "Element",
			"from": [ 7.5, 3.0427, 1.324 ],
			"to": [ 8.5, 4.05427, 7.17136 ],
			"rotation": { "origin": [ 8, 8.17174, -3.49882 ], "axis": "x", "angle": 45 },
			"faces": {
				"down": { "uv": [ 6, 13.5, 6.5, 14 ], "texture": "#0", "cullface": "down" },
				"up": { "uv": [ 6, 13.5, 6.5, 14 ], "texture": "#0", "cullface": "up" },
				"north": { "uv": [ 6, 13.5, 6.5, 14 ], "texture": "#0", "cullface": "north" },
				"south": { "uv": [ 6, 13.5, 6.5, 14 ], "texture": "#0", "cullface": "south" },
				"west": { "uv": [ 4, 13.5, 4.5, 14 ], "texture": "#0", "cullface": "west" },
				"east": { "uv": [ 4, 13.5, 4.5, 14 ], "texture": "#0", "cullface": "east" }
			}
		},
		{
			"__comment": "Element",
			"from": [ 7.5, 3.0427, 24.324 ],
			"to": [ 8.5, 4.05427, 30.17136 ],
			"rotation": { "origin": [ 8, 8.17174, 19.50118 ], "axis": "x", "angle": 45 },
			"faces": {
				"down": { "uv": [ 6, 13.5, 6.5, 14 ], "texture": "#0", "cullface": "down" },
				"up": { "uv": [ 6, 13.5, 6.5, 14 ], "texture": "#0", "cullface": "up" },
				"north": { "uv": [ 6, 13.5, 6.5, 14 ], "texture": "#0", "cullface": "north" },
				"south": { "uv": [ 6, 13.5, 6.5, 14 ], "texture": "#0", "cullface": "south" },
				"west": { "uv": [ 4, 13.5, 4.5, 14 ], "texture": "#0", "cullface": "west" },
				"east": { "uv": [ 4, 13.5, 4.5, 14 ], "texture": "#0", "cullface": "east" }
			}
		},
		{
			"__comment": "Element",
			"from": [ 7.5, -3, 0.4194 ],
			"to": [ 8.5, -2.29289, 1.1265 ],
			"faces": {
				"down": { "uv": [ 4, 13.5, 4.5, 14 ], "texture": "#0", "cullface": "down" },
				"up": { "uv": [ 4, 13.5, 4.5, 14 ], "texture": "#0", "cullface": "up" },
				"north": { "uv": [ 4, 13.5, 4.5, 14 ], "texture": "#0", "cullface": "north" },
				"south": { "uv": [ 4, 13.5, 4.5, 14 ], "texture": "#0", "cullface": "south" },
				"west": { "uv": [ 4, 13.5, 4.5, 14 ], "texture": "#0", "cullface": "west" },
				"east": { "uv": [ 4, 13.5, 4.5, 14 ], "texture": "#0", "cullface": "east" }
			}
		},
		{
			"__comment": "Element",
			"from": [ 7.5, -3, 23.4194 ],
			"to": [ 8.5, -2.29289, 24.1265 ],
			"faces": {
				"down": { "uv": [ 4, 13.5, 4.5, 14 ], "texture": "#0", "cullface": "down" },
				"up": { "uv": [ 4, 13.5, 4.5, 14 ], "texture": "#0", "cullface": "up" },
				"north": { "uv": [ 4, 13.5, 4.5, 14 ], "texture": "#0", "cullface": "north" },
				"south": { "uv": [ 4, 13.5, 4.5, 14 ], "texture": "#0", "cullface": "south" },
				"west": { "uv": [ 4, 13.5, 4.5, 14 ], "texture": "#0", "cullface": "west" },
				"east": { "uv": [ 4, 13.5, 4.5, 14 ], "texture": "#0", "cullface": "east" }
			}
		},
		{
			"__comment": "Element",
			"from": [ 3.2669, 20.0852, 19 ],
			"to": [ 4.2669, 26.0852, 20 ],
			"faces": {
				"down": { "uv": [ 6, 13.5, 6.5, 14 ], "texture": "#0", "cullface": "down" },
				"up": { "uv": [ 6, 13.5, 6.5, 14 ], "texture": "#0", "cullface": "up" },
				"north": { "uv": [ 6, 13.5, 6.5, 14 ], "texture": "#0", "cullface": "north" },
				"south": { "uv": [ 6, 13.5, 6.5, 14 ], "texture": "#0", "cullface": "south" },
				"west": { "uv": [ 6, 13.5, 6.5, 14 ], "texture": "#0", "cullface": "west" },
				"east": { "uv": [ 6, 13.5, 6.5, 14 ], "texture": "#0", "cullface": "east" }
			}
		},
		{
			"__comment": "Element",
			"from": [ 3.2669, 20.0852, -4 ],
			"to": [ 4.2669, 26.0852, -3 ],
			"faces": {
				"down": { "uv": [ 6, 13.5, 6.5, 14 ], "texture": "#0", "cullface": "down" },
				"up": { "uv": [ 6, 13.5, 6.5, 14 ], "texture": "#0", "cullface": "up" },
				"north": { "uv": [ 6, 13.5, 6.5, 14 ], "texture": "#0", "cullface": "north" },
				"south": { "uv": [ 6, 13.5, 6.5, 14 ], "texture": "#0", "cullface": "south" },
				"west": { "uv": [ 6, 13.5, 6.5, 14 ], "texture": "#0", "cullface": "west" },
				"east": { "uv": [ 6, 13.5, 6.5, 14 ], "texture": "#0", "cullface": "east" }
			}
		},
		{
			"__comment": "Element",
			"from": [ 0.5989, 17.6716, 19 ],
			"to": [ 5.8489, 18.6716, 20 ],
			"rotation": { "origin": [ 8, 12.17174, 19.50118 ], "axis": "z", "angle": -22.5 },
			"faces": {
				"down": { "uv": [ 6, 13.5, 6.5, 14 ], "texture": "#0", "cullface": "down" },
				"up": { "uv": [ 6, 13.5, 6.5, 14 ], "texture": "#0", "cullface": "up" },
				"north": { "uv": [ 6, 13.5, 6.5, 14 ], "texture": "#0", "cullface": "north" },
				"south": { "uv": [ 6, 13.5, 6.5, 14 ], "texture": "#0", "cullface": "south" },
				"west": { "uv": [ 6, 13.5, 6.5, 14 ], "texture": "#0", "cullface": "west" },
				"east": { "uv": [ 6, 13.5, 6.5, 14 ], "texture": "#0", "cullface": "east" }
			}
		},
		{
			"__comment": "Element",
			"from": [ 0.5989, 17.6716, -4 ],
			"to": [ 5.8489, 18.6716, -3 ],
			"rotation": { "origin": [ 8, 12.17174, -3.49882 ], "axis": "z", "angle": -22.5 },
			"faces": {
				"down": { "uv": [ 6, 13.5, 6.5, 14 ], "texture": "#0", "cullface": "down" },
				"up": { "uv": [ 6, 13.5, 6.5, 14 ], "texture": "#0", "cullface": "up" },
				"north": { "uv": [ 6, 13.5, 6.5, 14 ], "texture": "#0", "cullface": "north" },
				"south": { "uv": [ 6, 13.5, 6.5, 14 ], "texture": "#0", "cullface": "south" },
				"west": { "uv": [ 6, 13.5, 6.5, 14 ], "texture": "#0", "cullface": "west" },
				"east": { "uv": [ 6, 13.5, 6.5, 14 ], "texture": "#0", "cullface": "east" }
			}
		},
		{
			"__comment": "Element",
			"from": [ 10.1511, 17.6716, 19 ],
			"to": [ 15.4011, 18.6716, 20 ],
			"rotation": { "origin": [ 8, 12.17174, 19.50118 ], "axis": "z", "angle": 22.5 },
			"faces": {
				"down": { "uv": [ 6, 13.5, 6.5, 14 ], "texture": "#0", "cullface": "down" },
				"up": { "uv": [ 6, 13.5, 6.5, 14 ], "texture": "#0", "cullface": "up" },
				"north": { "uv": [ 6, 13.5, 6.5, 14 ], "texture": "#0", "cullface": "north" },
				"south": { "uv": [ 6, 13.5, 6.5, 14 ], "texture": "#0", "cullface": "south" },
				"west": { "uv": [ 6, 13.5, 6.5, 14 ], "texture": "#0", "cullface": "west" },
				"east": { "uv": [ 6, 13.5, 6.5, 14 ], "texture": "#0", "cullface": "east" }
			}
		},
		{
			"__comment": "Element",
			"from": [ 10.1511, 17.6716, -4 ],
			"to": [ 15.4011, 18.6716, -3 ],
			"rotation": { "origin": [ 8, 12.17174, -3.49882 ], "axis": "z", "angle": 22.5 },
			"faces": {
				"down": { "uv": [ 6, 13.5, 6.5, 14 ], "texture": "#0", "cullface": "down" },
				"up": { "uv": [ 6, 13.5, 6.5, 14 ], "texture": "#0", "cullface": "up" },
				"north": { "uv": [ 6, 13.5, 6.5, 14 ], "texture": "#0", "cullface": "north" },
				"south": { "uv": [ 6, 13.5, 6.5, 14 ], "texture": "#0", "cullface": "south" },
				"west": { "uv": [ 6, 13.5, 6.5, 14 ], "texture": "#0", "cullface": "west" },
				"east": { "uv": [ 6, 13.5, 6.5, 14 ], "texture": "#0", "cullface": "east" }
			}
		},
		{
			"__comment": "Element",
			"from": [ 11.733, 20.0852, 19 ],
			"to": [ 12.733, 26.0852, 20 ],
			"faces": {
				"down": { "uv": [ 6, 13.5, 6.5, 14 ], "texture": "#0", "cullface": "down" },
				"up": { "uv": [ 6, 13.5, 6.5, 14 ], "texture": "#0", "cullface": "up" },
				"north": { "uv": [ 6, 13.5, 6.5, 14 ], "texture": "#0", "cullface": "north" },
				"south": { "uv": [ 6, 13.5, 6.5, 14 ], "texture": "#0", "cullface": "south" },
				"west": { "uv": [ 6, 13.5, 6.5, 14 ], "texture": "#0", "cullface": "west" },
				"east": { "uv": [ 6, 13.5, 6.5, 14 ], "texture": "#0", "cullface": "east" }
			}
		},
		{
			"__comment": "Element",
			"from": [ 11.733, 20.0852, -4 ],
			"to": [ 12.733, 26.0852, -3 ],
			"faces": {
				"down": { "uv": [ 6, 13.5, 6.5, 14 ], "texture": "#0", "cullface": "down" },
				"up": { "uv": [ 6, 13.5, 6.5, 14 ], "texture": "#0", "cullface": "up" },
				"north": { "uv": [ 6, 13.5, 6.5, 14 ], "texture": "#0", "cullface": "north" },
				"south": { "uv": [ 6, 13.5, 6.5, 14 ], "texture": "#0", "cullface": "south" },
				"west": { "uv": [ 6, 13.5, 6.5, 14 ], "texture": "#0", "cullface": "west" },
				"east": { "uv": [ 6, 13.5, 6.5, 14 ], "texture": "#0", "cullface": "east" }
			}
		},
		{
			"__comment": "Element",
			"from": [ 4.5937, 26.1502, 19 ],
			"to": [ 5.5937, 28.1502, 20 ],
			"rotation": { "origin": [ 8, 8.17174, 19.50118 ], "axis": "z", "angle": -22.5 },
			"faces": {
				"down": { "uv": [ 6, 13.5, 6.5, 14 ], "texture": "#0", "cullface": "down" },
				"up": { "uv": [ 4, 13.5, 4.5, 14 ], "texture": "#0", "cullface": "up" },
				"north": { "uv": [ 6, 13.5, 6.5, 14 ], "texture": "#0", "cullface": "north" },
				"south": { "uv": [ 6, 13.5, 6.5, 14 ], "texture": "#0", "cullface": "south" },
				"west": { "uv": [ 6, 13.5, 6.5, 14 ], "texture": "#0", "cullface": "west" },
				"east": { "uv": [ 6, 13.5, 6.5, 14 ], "texture": "#0", "cullface": "east" }
			}
		},
		{
			"__comment": "Element",
			"from": [ 4.5937, 26.1502, -4 ],
			"to": [ 5.5937, 28.1502, -3 ],
			"rotation": { "origin": [ 8, 8.17174, -3.49882 ], "axis": "z", "angle": -22.5 },
			"faces": {
				"down": { "uv": [ 6, 13.5, 6.5, 14 ], "texture": "#0", "cullface": "down" },
				"up": { "uv": [ 4, 13.5, 4.5, 14 ], "texture": "#0", "cullface": "up" },
				"north": { "uv": [ 6, 13.5, 6.5, 14 ], "texture": "#0", "cullface": "north" },
				"south": { "uv": [ 6, 13.5, 6.5, 14 ], "texture": "#0", "cullface": "south" },
				"west": { "uv": [ 6, 13.5, 6.5, 14 ], "texture": "#0", "cullface": "west" },
				"east": { "uv": [ 6, 13.5, 6.5, 14 ], "texture": "#0", "cullface": "east" }
			}
		},
		{
			"__comment": "Element",
			"from": [ 10.4063, 26.1502, 19 ],
			"to": [ 11.4063, 28.1502, 20 ],
			"rotation": { "origin": [ 8, 8.17174, 19.50118 ], "axis": "z", "angle": 22.5 },
			"faces": {
				"down": { "uv": [ 6, 13.5, 6.5, 14 ], "texture": "#0", "cullface": "down" },
				"up": { "uv": [ 4, 13.5, 4.5, 14 ], "texture": "#0", "cullface": "up" },
				"north": { "uv": [ 6, 13.5, 6.5, 14 ], "texture": "#0", "cullface": "north" },
				"south": { "uv": [ 6, 13.5, 6.5, 14 ], "texture": "#0", "cullface": "south" },
				"west": { "uv": [ 6, 13.5, 6.5, 14 ], "texture": "#0", "cullface": "west" },
				"east": { "uv": [ 6, 13.5, 6.5, 14 ], "texture": "#0", "cullface": "east" }
			}
		},
		{
			"__comment": "Element",
			"from": [ 10.4063, 26.1502, -4 ],
			"to": [ 11.4063, 28.1502, -3 ],
			"rotation": { "origin": [ 8, 8.17174, -3.49882 ], "axis": "z", "angle": 22.5 },
			"faces": {
				"down": { "uv": [ 6, 13.5, 6.5, 14 ], "texture": "#0", "cullface": "down" },
				"up": { "uv": [ 4, 13.5, 4.5, 14 ], "texture": "#0", "cullface": "up" },
				"north": { "uv": [ 6, 13.5, 6.5, 14 ], "texture": "#0", "cullface": "north" },
				"south": { "uv": [ 6, 13.5, 6.5, 14 ], "texture": "#0", "cullface": "south" },
				"west": { "uv": [ 6, 13.5, 6.5, 14 ], "texture": "#0", "cullface": "west" },
				"east": { "uv": [ 6, 13.5, 6.5, 14 ], "texture": "#0", "cullface": "east" }
			}
		},
		{
			"__comment": "Element",
			"from": [ 4.267, 25.0852, 19 ],
			"to": [ 11.7331, 26.0852, 20 ],
			"faces": {
				"down": { "uv": [ 4, 13.5, 4.5, 14 ], "texture": "#0", "cullface": "down" },
				"up": { "uv": [ 4, 13.5, 4.5, 14 ], "texture": "#0", "cullface": "up" },
				"north": { "uv": [ 4, 13.5, 4.5, 14 ], "texture": "#0", "cullface": "north" },
				"south": { "uv": [ 4, 13.5, 4.5, 14 ], "texture": "#0", "cullface": "south" },
				"west": { "uv": [ 4, 13.5, 4.5, 14 ], "texture": "#0", "cullface": "west" },
				"east": { "uv": [ 4, 13.5, 4.5, 14 ], "texture": "#0", "cullface": "east" }
			}
		},
		{
			"__comment": "Element",
			"from": [ 4.267, 25.0852, -4 ],
			"to": [ 11.7331, 26.0852, -3 ],
			"faces": {
				"down": { "uv": [ 4, 13.5, 4.5, 14 ], "texture": "#0", "cullface": "down" },
				"up": { "uv": [ 4, 13.5, 4.5, 14 ], "texture": "#0", "cullface": "up" },
				"north": { "uv": [ 4, 13.5, 4.5, 14 ], "texture": "#0", "cullface": "north" },
				"south": { "uv": [ 4, 13.5, 4.5, 14 ], "texture": "#0", "cullface": "south" },
				"west": { "uv": [ 4, 13.5, 4.5, 14 ], "texture": "#0", "cullface": "west" },
				"east": { "uv": [ 4, 13.5, 4.5, 14 ], "texture": "#0", "cullface": "east" }
			}
		},
		{
			"__comment": "Element",
			"from": [ 7.5, 26.1, 17 ],
			"to": [ 8.5, 27.1, 20 ],
			"faces": {
				"down": { "uv": [ 6, 13.5, 6.5, 14 ], "texture": "#0", "cullface": "down" },
				"up": { "uv": [ 6, 13.5, 6.5, 14 ], "texture": "#0", "cullface": "up" },
				"north": { "uv": [ 6, 13.5, 6.5, 14 ], "texture": "#0", "cullface": "north" },
				"south": { "uv": [ 6, 13.5, 6.5, 14 ], "texture": "#0", "cullface": "south" },
				"west": { "uv": [ 4, 13.5, 4.5, 14 ], "texture": "#0", "cullface": "west" },
				"east": { "uv": [ 4, 13.5, 4.5, 14 ], "texture": "#0", "cullface": "east" }
			}
		},
		{
			"__comment": "Element",
			"from": [ 7.5, 26.1, -4 ],
			"to": [ 8.5, 27.1, -1 ],
			"faces": {
				"down": { "uv": [ 6, 13.5, 6.5, 14 ], "texture": "#0", "cullface": "down" },
				"up": { "uv": [ 6, 13.5, 6.5, 14 ], "texture": "#0", "cullface": "up" },
				"north": { "uv": [ 6, 13.5, 6.5, 14 ], "texture": "#0", "cullface": "north" },
				"south": { "uv": [ 6, 13.5, 6.5, 14 ], "texture": "#0", "cullface": "south" },
				"west": { "uv": [ 4, 13.5, 4.5, 14 ], "texture": "#0", "cullface": "west" },
				"east": { "uv": [ 4, 13.5, 4.5, 14 ], "texture": "#0", "cullface": "east" }
			}
		},
		{
			"__comment": "Element",
			"from": [ 7.5, 26.636, 14.3055 ],
			"to": [ 8.5, 27.636, 17.3055 ],
			"rotation": { "origin": [ 8, 27.13596, 15.80552 ], "axis": "x", "angle": 22.5 },
			"faces": {
				"down": { "uv": [ 6, 13.5, 6.5, 14 ], "texture": "#0", "cullface": "down" },
				"up": { "uv": [ 6, 13.5, 6.5, 14 ], "texture": "#0", "cullface": "up" },
				"north": { "uv": [ 6, 13.5, 6.5, 14 ], "texture": "#0", "cullface": "north" },
				"south": { "uv": [ 6, 13.5, 6.5, 14 ], "texture": "#0", "cullface": "south" },
				"west": { "uv": [ 4, 13.5, 4.5, 14 ], "texture": "#0", "cullface": "west" },
				"east": { "uv": [ 4, 13.5, 4.5, 14 ], "texture": "#0", "cullface": "east" }
			}
		},
		{
			"__comment": "Element",
			"from": [ 7.5, 26.636, -1.3055 ],
			"to": [ 8.5, 27.636, 1.6945 ],
			"rotation": { "origin": [ 8, 27.13596, 0.19448 ], "axis": "x", "angle": -22.5 },
			"faces": {
				"down": { "uv": [ 6, 13.5, 6.5, 14 ], "texture": "#0", "cullface": "down" },
				"up": { "uv": [ 6, 13.5, 6.5, 14 ], "texture": "#0", "cullface": "up" },
				"north": { "uv": [ 6, 13.5, 6.5, 14 ], "texture": "#0", "cullface": "north" },
				"south": { "uv": [ 6, 13.5, 6.5, 14 ], "texture": "#0", "cullface": "south" },
				"west": { "uv": [ 4, 13.5, 4.5, 14 ], "texture": "#0", "cullface": "west" },
				"east": { "uv": [ 4, 13.5, 4.5, 14 ], "texture": "#0", "cullface": "east" }
			}
		},
		{
			"__comment": "Element",
			"from": [ 7.5, 26.636, 19.6945 ],
			"to": [ 8.5, 27.636, 21.6945 ],
			"rotation": { "origin": [ 8, 27.13596, 21.19448 ], "axis": "x", "angle": -22.5 },
			"faces": {
				"down": { "uv": [ 6, 13.5, 6.5, 14 ], "texture": "#0", "cullface": "down" },
				"up": { "uv": [ 6, 13.5, 6.5, 14 ], "texture": "#0", "cullface": "up" },
				"north": { "uv": [ 6, 13.5, 6.5, 14 ], "texture": "#0", "cullface": "north" },
				"south": { "uv": [ 4, 13.5, 4.5, 14 ], "texture": "#0", "cullface": "south" },
				"west": { "uv": [ 4, 13.5, 4.5, 14 ], "texture": "#0", "cullface": "west" },
				"east": { "uv": [ 4, 13.5, 4.5, 14 ], "texture": "#0", "cullface": "east" }
			}
		},
		{
			"__comment": "Element",
			"from": [ 7.5, 26.636, -5.6945 ],
			"to": [ 8.5, 27.636, -3.6945 ],
			"rotation": { "origin": [ 8, 27.13596, -5.19448 ], "axis": "x", "angle": 22.5 },
			"faces": {
				"down": { "uv": [ 6, 13.5, 6.5, 14 ], "texture": "#0", "cullface": "down" },
				"up": { "uv": [ 6, 13.5, 6.5, 14 ], "texture": "#0", "cullface": "up" },
				"north": { "uv": [ 4, 13.5, 4.5, 14 ], "texture": "#0", "cullface": "north" },
				"south": { "uv": [ 6, 13.5, 6.5, 14 ], "texture": "#0", "cullface": "south" },
				"west": { "uv": [ 4, 13.5, 4.5, 14 ], "texture": "#0", "cullface": "west" },
				"east": { "uv": [ 4, 13.5, 4.5, 14 ], "texture": "#0", "cullface": "east" }
			}
		},
		{
			"__comment": "Element",
			"from": [ 7.5, 28.8694, 12.3142 ],
			"to": [ 8.5, 29.8694, 15.3142 ],
			"rotation": { "origin": [ 8, 29.36937, 12.81415 ], "axis": "x", "angle": 45 },
			"faces": {
				"down": { "uv": [ 6, 13.5, 6.5, 14 ], "texture": "#0", "cullface": "down" },
				"up": { "uv": [ 6, 13.5, 6.5, 14 ], "texture": "#0", "cullface": "up" },
				"north": { "uv": [ 6, 13.5, 6.5, 14 ], "texture": "#0", "cullface": "north" },
				"south": { "uv": [ 6, 13.5, 6.5, 14 ], "texture": "#0", "cullface": "south" },
				"west": { "uv": [ 4, 13.5, 4.5, 14 ], "texture": "#0", "cullface": "west" },
				"east": { "uv": [ 4, 13.5, 4.5, 14 ], "texture": "#0", "cullface": "east" }
			}
		},
		{
			"__comment": "Element",
			"from": [ 7.5, 28.8694, 0.6858 ],
			"to": [ 8.5, 29.8694, 3.6858 ],
			"rotation": { "origin": [ 8, 29.36937, 3.18585 ], "axis": "x", "angle": -45 },
			"faces": {
				"down": { "uv": [ 6, 13.5, 6.5, 14 ], "texture": "#0", "cullface": "down" },
				"up": { "uv": [ 6, 13.5, 6.5, 14 ], "texture": "#0", "cullface": "up" },
				"north": { "uv": [ 6, 13.5, 6.5, 14 ], "texture": "#0", "cullface": "north" },
				"south": { "uv": [ 6, 13.5, 6.5, 14 ], "texture": "#0", "cullface": "south" },
				"west": { "uv": [ 4, 13.5, 4.5, 14 ], "texture": "#0", "cullface": "west" },
				"east": { "uv": [ 4, 13.5, 4.5, 14 ], "texture": "#0", "cullface": "east" }
			}
		},
		{
			"__comment": "Element",
			"from": [ 7.5, 29.6886, 8.737 ],
			"to": [ 8.5, 30.6886, 12.737 ],
			"rotation": { "origin": [ 8, 30.18856, 11.23699 ], "axis": "x", "angle": 22.5 },
			"faces": {
				"down": { "uv": [ 6, 13.5, 6.5, 14 ], "texture": "#0", "cullface": "down" },
				"up": { "uv": [ 6, 13.5, 6.5, 14 ], "texture": "#0", "cullface": "up" },
				"north": { "uv": [ 6, 13.5, 6.5, 14 ], "texture": "#0", "cullface": "north" },
				"south": { "uv": [ 6, 13.5, 6.5, 14 ], "texture": "#0", "cullface": "south" },
				"west": { "uv": [ 4, 13.5, 4.5, 14 ], "texture": "#0", "cullface": "west" },
				"east": { "uv": [ 4, 13.5, 4.5, 14 ], "texture": "#0", "cullface": "east" }
			}
		},
		{
			"__comment": "Element",
			"from": [ 7.5, 29.6886, 3.263 ],
			"to": [ 8.5, 30.6886, 7.263 ],
			"rotation": { "origin": [ 8, 30.18856, 4.76301 ], "axis": "x", "angle": -22.5 },
			"faces": {
				"down": { "uv": [ 6, 13.5, 6.5, 14 ], "texture": "#0", "cullface": "down" },
				"up": { "uv": [ 6, 13.5, 6.5, 14 ], "texture": "#0", "cullface": "up" },
				"north": { "uv": [ 6, 13.5, 6.5, 14 ], "texture": "#0", "cullface": "north" },
				"south": { "uv": [ 6, 13.5, 6.5, 14 ], "texture": "#0", "cullface": "south" },
				"west": { "uv": [ 4, 13.5, 4.5, 14 ], "texture": "#0", "cullface": "west" },
				"east": { "uv": [ 4, 13.5, 4.5, 14 ], "texture": "#0", "cullface": "east" }
			}
		},
		{
			"__comment": "Element",
			"from": [ 7.5, 30.6072, 6.8814 ],
			"to": [ 8.5, 31.6072, 9.11866 ],
			"faces": {
				"down": { "uv": [ 6, 13.5, 6.5, 14 ], "texture": "#0", "cullface": "down" },
				"up": { "uv": [ 6, 13.5, 6.5, 14 ], "texture": "#0", "cullface": "up" },
				"north": { "uv": [ 6, 13.5, 6.5, 14 ], "texture": "#0", "cullface": "north" },
				"south": { "uv": [ 6, 13.5, 6.5, 14 ], "texture": "#0", "cullface": "south" },
				"west": { "uv": [ 4, 13.5, 4.5, 14 ], "texture": "#0", "cullface": "west" },
				"east": { "uv": [ 4, 13.5, 4.5, 14 ], "texture": "#0", "cullface": "east" }
			}
		},
		{
			"__comment": "Element",
			"from": [ 7.35, 10.5, 6.425 ],
			"to": [ 8.65, 26.5, 9.54632 ],
			"faces": {
				"down": { "uv": [ 7.5, 7, 8, 7.5 ], "texture": "#1_1", "cullface": "down" },
				"up": { "uv": [ 7.5, 7, 8, 7.5 ], "texture": "#1_1", "cullface": "up" },
				"north": { "uv": [ 7.5, 7, 8, 7.5 ], "texture": "#1_1", "cullface": "north" },
				"south": { "uv": [ 7.5, 7, 8, 7.5 ], "texture": "#1_1", "cullface": "south" },
				"west": { "uv": [ 7.5, 7, 8, 7.5 ], "texture": "#1_1", "cullface": "west" },
				"east": { "uv": [ 7.5, 7, 8, 7.5 ], "texture": "#1_1", "cullface": "east" }
			}
		},
		{
			"__comment": "Element",
			"from": [ 6.4293, 10.5, 6.8064 ],
			"to": [ 7.71717, 26.5, 9.932751 ],
			"rotation": { "origin": [ 7.07322, 24, 7.05888 ], "axis": "y", "angle": 45 },
			"faces": {
				"down": { "uv": [ 7.5, 7, 8, 7.5 ], "texture": "#1_1", "cullface": "down" },
				"up": { "uv": [ 7.5, 7, 8, 7.5 ], "texture": "#1_1", "cullface": "up" },
				"north": { "uv": [ 7.5, 7, 8, 7.5 ], "texture": "#1_1", "cullface": "north" },
				"south": { "uv": [ 7.5, 7, 8, 7.5 ], "texture": "#1_1", "cullface": "south" },
				"west": { "uv": [ 7.5, 7, 8, 7.5 ], "texture": "#1_1", "cullface": "west" },
				"east": { "uv": [ 7.5, 7, 8, 7.5 ], "texture": "#1_1", "cullface": "east" }
			}
		},
		{
			"__comment": "Element",
			"from": [ 6.4368, 10.5, 8.268499 ],
			"to": [ 9.563141, 26.5, 9.556369 ],
			"rotation": { "origin": [ 6.88128, 24, 8.44905 ], "axis": "y", "angle": 45 },
			"faces": {
				"down": { "uv": [ 7.5, 7, 8, 7.5 ], "texture": "#1_1", "cullface": "down" },
				"up": { "uv": [ 7.5, 7, 8, 7.5 ], "texture": "#1_1", "cullface": "up" },
				"north": { "uv": [ 7.5, 7, 8, 7.5 ], "texture": "#1_1", "cullface": "north" },
				"south": { "uv": [ 7.5, 7, 8, 7.5 ], "texture": "#1_1", "cullface": "south" },
				"west": { "uv": [ 7.5, 7, 8, 7.5 ], "texture": "#1_1", "cullface": "west" },
				"east": { "uv": [ 7.5, 7, 8, 7.5 ], "texture": "#1_1", "cullface": "east" }
			}
		},
		{
			"__comment": "Element",
			"from": [ 6.4393, 10.5, 7.3357 ],
			"to": [ 9.56062, 26.5, 8.6357 ],
			"faces": {
				"down": { "uv": [ 7.5, 7, 8, 7.5 ], "texture": "#1_1", "cullface": "down" },
				"up": { "uv": [ 7.5, 7, 8, 7.5 ], "texture": "#1_1", "cullface": "up" },
				"north": { "uv": [ 7.5, 7, 8, 7.5 ], "texture": "#1_1", "cullface": "north" },
				"south": { "uv": [ 7.5, 7, 8, 7.5 ], "texture": "#1_1", "cullface": "south" },
				"west": { "uv": [ 7.5, 7, 8, 7.5 ], "texture": "#1_1", "cullface": "west" },
				"east": { "uv": [ 7.5, 7, 8, 7.5 ], "texture": "#1_1", "cullface": "east" }
			}
		},
		{
			"__comment": "Element",
			"from": [ 7.45, 11.15, 3.175 ],
			"to": [ 8.55, 25.85, 5.79632 ],
			"faces": {
				"down": { "uv": [ 7.5, 7, 8, 7.5 ], "texture": "#1_1", "cullface": "down" },
				"up": { "uv": [ 7.5, 7, 8, 7.5 ], "texture": "#1_1", "cullface": "up" },
				"north": { "uv": [ 7.5, 7, 8, 7.5 ], "texture": "#1_1", "cullface": "north" },
				"south": { "uv": [ 7.5, 7, 8, 7.5 ], "texture": "#1_1", "cullface": "south" },
				"west": { "uv": [ 7.5, 7, 8, 7.5 ], "texture": "#1_1", "cullface": "west" },
				"east": { "uv": [ 7.5, 7, 8, 7.5 ], "texture": "#1_1", "cullface": "east" }
			}
		},
		{
			"__comment": "Element",
			"from": [ 6.5354, 11.15, 3.5539 ],
			"to": [ 7.61113, 25.85, 6.18527 ],
			"rotation": { "origin": [ 7.07322, 25.35, 3.55888 ], "axis": "y", "angle": 45 },
			"faces": {
				"down": { "uv": [ 7.5, 7, 8, 7.5 ], "texture": "#1_1", "cullface": "down" },
				"up": { "uv": [ 7.5, 7, 8, 7.5 ], "texture": "#1_1", "cullface": "up" },
				"north": { "uv": [ 7.5, 7, 8, 7.5 ], "texture": "#1_1", "cullface": "north" },
				"south": { "uv": [ 7.5, 7, 8, 7.5 ], "texture": "#1_1", "cullface": "south" },
				"west": { "uv": [ 7.5, 7, 8, 7.5 ], "texture": "#1_1", "cullface": "west" },
				"east": { "uv": [ 7.5, 7, 8, 7.5 ], "texture": "#1_1", "cullface": "east" }
			}
		},
		{
			"__comment": "Element",
			"from": [ 6.6843, 11.15, 4.8746 ],
			"to": [ 9.31568, 25.85, 5.95033 ],
			"rotation": { "origin": [ 6.88128, 25.35, 4.94905 ], "axis": "y", "angle": 45 },
			"faces": {
				"down": { "uv": [ 7.5, 7, 8, 7.5 ], "texture": "#1_1", "cullface": "down" },
				"up": { "uv": [ 7.5, 7, 8, 7.5 ], "texture": "#1_1", "cullface": "up" },
				"north": { "uv": [ 7.5, 7, 8, 7.5 ], "texture": "#1_1", "cullface": "north" },
				"south": { "uv": [ 7.5, 7, 8, 7.5 ], "texture": "#1_1", "cullface": "south" },
				"west": { "uv": [ 7.5, 7, 8, 7.5 ], "texture": "#1_1", "cullface": "west" },
				"east": { "uv": [ 7.5, 7, 8, 7.5 ], "texture": "#1_1", "cullface": "east" }
			}
		},
		{
			"__comment": "Element",
			"from": [ 6.6893, 11.15, 3.9357 ],
			"to": [ 9.31062, 25.85, 5.0357 ],
			"faces": {
				"down": { "uv": [ 7.5, 7, 8, 7.5 ], "texture": "#1_1", "cullface": "down" },
				"up": { "uv": [ 7.5, 7, 8, 7.5 ], "texture": "#1_1", "cullface": "up" },
				"north": { "uv": [ 7.5, 7, 8, 7.5 ], "texture": "#1_1", "cullface": "north" },
				"south": { "uv": [ 7.5, 7, 8, 7.5 ], "texture": "#1_1", "cullface": "south" },
				"west": { "uv": [ 7.5, 7, 8, 7.5 ], "texture": "#1_1", "cullface": "west" },
				"east": { "uv": [ 7.5, 7, 8, 7.5 ], "texture": "#1_1", "cullface": "east" }
			}
		},
		{
			"__comment": "Element",
			"from": [ 7.45, 11.15, 10.175 ],
			"to": [ 8.55, 25.85, 12.79632 ],
			"faces": {
				"down": { "uv": [ 7.5, 7, 8, 7.5 ], "texture": "#1_1", "cullface": "down" },
				"up": { "uv": [ 7.5, 7, 8, 7.5 ], "texture": "#1_1", "cullface": "up" },
				"north": { "uv": [ 7.5, 7, 8, 7.5 ], "texture": "#1_1", "cullface": "north" },
				"south": { "uv": [ 7.5, 7, 8, 7.5 ], "texture": "#1_1", "cullface": "south" },
				"west": { "uv": [ 7.5, 7, 8, 7.5 ], "texture": "#1_1", "cullface": "west" },
				"east": { "uv": [ 7.5, 7, 8, 7.5 ], "texture": "#1_1", "cullface": "east" }
			}
		},
		{
			"__comment": "Element",
			"from": [ 6.5354, 11.15, 10.5539 ],
			"to": [ 7.61113, 25.85, 13.18527 ],
			"rotation": { "origin": [ 7.07322, 25.35, 10.55888 ], "axis": "y", "angle": 45 },
			"faces": {
				"down": { "uv": [ 7.5, 7, 8, 7.5 ], "texture": "#1_1", "cullface": "down" },
				"up": { "uv": [ 7.5, 7, 8, 7.5 ], "texture": "#1_1", "cullface": "up" },
				"north": { "uv": [ 7.5, 7, 8, 7.5 ], "texture": "#1_1", "cullface": "north" },
				"south": { "uv": [ 7.5, 7, 8, 7.5 ], "texture": "#1_1", "cullface": "south" },
				"west": { "uv": [ 7.5, 7, 8, 7.5 ], "texture": "#1_1", "cullface": "west" },
				"east": { "uv": [ 7.5, 7, 8, 7.5 ], "texture": "#1_1", "cullface": "east" }
			}
		},
		{
			"__comment": "Element",
			"from": [ 6.6843, 11.15, 11.8746 ],
			"to": [ 9.31568, 25.85, 12.95033 ],
			"rotation": { "origin": [ 6.88128, 25.35, 11.94905 ], "axis": "y", "angle": 45 },
			"faces": {
				"down": { "uv": [ 7.5, 7, 8, 7.5 ], "texture": "#1_1", "cullface": "down" },
				"up": { "uv": [ 7.5, 7, 8, 7.5 ], "texture": "#1_1", "cullface": "up" },
				"north": { "uv": [ 7.5, 7, 8, 7.5 ], "texture": "#1_1", "cullface": "north" },
				"south": { "uv": [ 7.5, 7, 8, 7.5 ], "texture": "#1_1", "cullface": "south" },
				"west": { "uv": [ 7.5, 7, 8, 7.5 ], "texture": "#1_1", "cullface": "west" },
				"east": { "uv": [ 7.5, 7, 8, 7.5 ], "texture": "#1_1", "cullface": "east" }
			}
		},
		{
			"__comment": "Element",
			"from": [ 6.6893, 11.15, 10.9357 ],
			"to": [ 9.31062, 25.85, 12.0357 ],
			"faces": {
				"down": { "uv": [ 7.5, 7, 8, 7.5 ], "texture": "#1_1", "cullface": "down" },
				"up": { "uv": [ 7.5, 7, 8, 7.5 ], "texture": "#1_1", "cullface": "up" },
				"north": { "uv": [ 7.5, 7, 8, 7.5 ], "texture": "#1_1", "cullface": "north" },
				"south": { "uv": [ 7.5, 7, 8, 7.5 ], "texture": "#1_1", "cullface": "south" },
				"west": { "uv": [ 7.5, 7, 8, 7.5 ], "texture": "#1_1", "cullface": "west" },
				"east": { "uv": [ 7.5, 7, 8, 7.5 ], "texture": "#1_1", "cullface": "east" }
			}
		},
		{
			"__comment": "Element",
			"from": [ 7.55, 13, 13.425 ],
			"to": [ 8.449999, 24, 15.54632 ],
			"faces": {
				"down": { "uv": [ 7.5, 7, 8, 7.5 ], "texture": "#1_1", "cullface": "down" },
				"up": { "uv": [ 7.5, 7, 8, 7.5 ], "texture": "#1_1", "cullface": "up" },
				"north": { "uv": [ 7.5, 7, 8, 7.5 ], "texture": "#1_1", "cullface": "north" },
				"south": { "uv": [ 7.5, 7, 8, 7.5 ], "texture": "#1_1", "cullface": "south" },
				"west": { "uv": [ 7.5, 7, 8, 7.5 ], "texture": "#1_1", "cullface": "west" },
				"east": { "uv": [ 7.5, 7, 8, 7.5 ], "texture": "#1_1", "cullface": "east" }
			}
		},
		{
			"__comment": "Element",
			"from": [ 7.5682, 13, 13.4175 ],
			"to": [ 8.431799, 24, 15.5539 ],
			"rotation": { "origin": [ 8, 24.5, 14.48566 ], "axis": "y", "angle": 45 },
			"faces": {
				"down": { "uv": [ 7.5, 7, 8, 7.5 ], "texture": "#1_1", "cullface": "down" },
				"up": { "uv": [ 7.5, 7, 8, 7.5 ], "texture": "#1_1", "cullface": "up" },
				"north": { "uv": [ 7.5, 7, 8, 7.5 ], "texture": "#1_1", "cullface": "north" },
				"south": { "uv": [ 7.5, 7, 8, 7.5 ], "texture": "#1_1", "cullface": "south" },
				"west": { "uv": [ 7.5, 7, 8, 7.5 ], "texture": "#1_1", "cullface": "west" },
				"east": { "uv": [ 7.5, 7, 8, 7.5 ], "texture": "#1_1", "cullface": "east" }
			}
		},
		{
			"__comment": "Element",
			"from": [ 6.9318, 13, 14.0539 ],
			"to": [ 9.0682, 24, 14.9175 ],
			"rotation": { "origin": [ 8, 24.5, 14.48566 ], "axis": "y", "angle": 45 },
			"faces": {
				"down": { "uv": [ 7.5, 7, 8, 7.5 ], "texture": "#1_1", "cullface": "down" },
				"up": { "uv": [ 7.5, 7, 8, 7.5 ], "texture": "#1_1", "cullface": "up" },
				"north": { "uv": [ 7.5, 7, 8, 7.5 ], "texture": "#1_1", "cullface": "north" },
				"south": { "uv": [ 7.5, 7, 8, 7.5 ], "texture": "#1_1", "cullface": "south" },
				"west": { "uv": [ 7.5, 7, 8, 7.5 ], "texture": "#1_1", "cullface": "west" },
				"east": { "uv": [ 7.5, 7, 8, 7.5 ], "texture": "#1_1", "cullface": "east" }
			}
		},
		{
			"__comment": "Element",
			"from": [ 6.9393, 13, 14.0357 ],
			"to": [ 9.06062, 24, 14.9357 ],
			"faces": {
				"down": { "uv": [ 7.5, 7, 8, 7.5 ], "texture": "#1_1", "cullface": "down" },
				"up": { "uv": [ 7.5, 7, 8, 7.5 ], "texture": "#1_1", "cullface": "up" },
				"north": { "uv": [ 7.5, 7, 8, 7.5 ], "texture": "#1_1", "cullface": "north" },
				"south": { "uv": [ 7.5, 7, 8, 7.5 ], "texture": "#1_1", "cullface": "south" },
				"west": { "uv": [ 7.5, 7, 8, 7.5 ], "texture": "#1_1", "cullface": "west" },
				"east": { "uv": [ 7.5, 7, 8, 7.5 ], "texture": "#1_1", "cullface": "east" }
			}
		},
		{
			"__comment": "Element",
			"from": [ 7.55, 13, 0.425 ],
			"to": [ 8.449999, 24, 2.54632 ],
			"faces": {
				"down": { "uv": [ 7.5, 7, 8, 7.5 ], "texture": "#1_1", "cullface": "down" },
				"up": { "uv": [ 7.5, 7, 8, 7.5 ], "texture": "#1_1", "cullface": "up" },
				"north": { "uv": [ 7.5, 7, 8, 7.5 ], "texture": "#1_1", "cullface": "north" },
				"south": { "uv": [ 7.5, 7, 8, 7.5 ], "texture": "#1_1", "cullface": "south" },
				"west": { "uv": [ 7.5, 7, 8, 7.5 ], "texture": "#1_1", "cullface": "west" },
				"east": { "uv": [ 7.5, 7, 8, 7.5 ], "texture": "#1_1", "cullface": "east" }
			}
		},
		{
			"__comment": "Element",
			"from": [ 7.5682, 13, 0.4175 ],
			"to": [ 8.431799, 24, 2.5539 ],
			"rotation": { "origin": [ 8, 24.5, 1.48566 ], "axis": "y", "angle": 45 },
			"faces": {
				"down": { "uv": [ 7.5, 7, 8, 7.5 ], "texture": "#1_1", "cullface": "down" },
				"up": { "uv": [ 7.5, 7, 8, 7.5 ], "texture": "#1_1", "cullface": "up" },
				"north": { "uv": [ 7.5, 7, 8, 7.5 ], "texture": "#1_1", "cullface": "north" },
				"south": { "uv": [ 7.5, 7, 8, 7.5 ], "texture": "#1_1", "cullface": "south" },
				"west": { "uv": [ 7.5, 7, 8, 7.5 ], "texture": "#1_1", "cullface": "west" },
				"east": { "uv": [ 7.5, 7, 8, 7.5 ], "texture": "#1_1", "cullface": "east" }
			}
		},
		{
			"__comment": "Element",
			"from": [ 6.9318, 13, 1.0539 ],
			"to": [ 9.0682, 24, 1.9175 ],
			"rotation": { "origin": [ 8, 24.5, 1.48566 ], "axis": "y", "angle": 45 },
			"faces": {
				"down": { "uv": [ 7.5, 7, 8, 7.5 ], "texture": "#1_1", "cullface": "down" },
				"up": { "uv": [ 7.5, 7, 8, 7.5 ], "texture": "#1_1", "cullface": "up" },
				"north": { "uv": [ 7.5, 7, 8, 7.5 ], "texture": "#1_1", "cullface": "north" },
				"south": { "uv": [ 7.5, 7, 8, 7.5 ], "texture": "#1_1", "cullface": "south" },
				"west": { "uv": [ 7.5, 7, 8, 7.5 ], "texture": "#1_1", "cullface": "west" },
				"east": { "uv": [ 7.5, 7, 8, 7.5 ], "texture": "#1_1", "cullface": "east" }
			}
		},
		{
			"__comment": "Element",
			"from": [ 6.9393, 13, 1.0357 ],
			"to": [ 9.06062, 24, 1.9357 ],
			"faces": {
				"down": { "uv": [ 7.5, 7, 8, 7.5 ], "texture": "#1_1", "cullface": "down" },
				"up": { "uv": [ 7.5, 7, 8, 7.5 ], "texture": "#1_1", "cullface": "up" },
				"north": { "uv": [ 7.5, 7, 8, 7.5 ], "texture": "#1_1", "cullface": "north" },
				"south": { "uv": [ 7.5, 7, 8, 7.5 ], "texture": "#1_1", "cullface": "south" },
				"west": { "uv": [ 7.5, 7, 8, 7.5 ], "texture": "#1_1", "cullface": "west" },
				"east": { "uv": [ 7.5, 7, 8, 7.5 ], "texture": "#1_1", "cullface": "east" }
			}
		},
		{
			"__comment": "Element",
			"from": [ 7.65, 13.5, -1.825 ],
			"to": [ 8.35, 23.5, -0.2036799 ],
			"faces": {
				"down": { "uv": [ 7.5, 7, 8, 7.5 ], "texture": "#1_1", "cullface": "down" },
				"up": { "uv": [ 7.5, 7, 8, 7.5 ], "texture": "#1_1", "cullface": "up" },
				"north": { "uv": [ 7.5, 7, 8, 7.5 ], "texture": "#1_1", "cullface": "north" },
				"south": { "uv": [ 7.5, 7, 8, 7.5 ], "texture": "#1_1", "cullface": "south" },
				"west": { "uv": [ 7.5, 7, 8, 7.5 ], "texture": "#1_1", "cullface": "west" },
				"east": { "uv": [ 7.5, 7, 8, 7.5 ], "texture": "#1_1", "cullface": "east" }
			}
		},
		{
			"__comment": "Element",
			"from": [ 7.6743, 13.5, -1.835 ],
			"to": [ 8.325779, 23.5, -0.1935799 ],
			"rotation": { "origin": [ 8, 25, -1.01434 ], "axis": "y", "angle": 45 },
			"faces": {
				"down": { "uv": [ 7.5, 7, 8, 7.5 ], "texture": "#1_1", "cullface": "down" },
				"up": { "uv": [ 7.5, 7, 8, 7.5 ], "texture": "#1_1", "cullface": "up" },
				"north": { "uv": [ 7.5, 7, 8, 7.5 ], "texture": "#1_1", "cullface": "north" },
				"south": { "uv": [ 7.5, 7, 8, 7.5 ], "texture": "#1_1", "cullface": "south" },
				"west": { "uv": [ 7.5, 7, 8, 7.5 ], "texture": "#1_1", "cullface": "west" },
				"east": { "uv": [ 7.5, 7, 8, 7.5 ], "texture": "#1_1", "cullface": "east" }
			}
		},
		{
			"__comment": "Element",
			"from": [ 7.1793, 13.5, -1.3401 ],
			"to": [ 8.820721, 23.5, -0.6886199 ],
			"rotation": { "origin": [ 8, 25, -1.01434 ], "axis": "y", "angle": 45 },
			"faces": {
				"down": { "uv": [ 7.5, 7, 8, 7.5 ], "texture": "#1_1", "cullface": "down" },
				"up": { "uv": [ 7.5, 7, 8, 7.5 ], "texture": "#1_1", "cullface": "up" },
				"north": { "uv": [ 7.5, 7, 8, 7.5 ], "texture": "#1_1", "cullface": "north" },
				"south": { "uv": [ 7.5, 7, 8, 7.5 ], "texture": "#1_1", "cullface": "south" },
				"west": { "uv": [ 7.5, 7, 8, 7.5 ], "texture": "#1_1", "cullface": "west" },
				"east": { "uv": [ 7.5, 7, 8, 7.5 ], "texture": "#1_1", "cullface": "east" }
			}
		},
		{
			"__comment": "Element",
			"from": [ 7.1893, 13.5, -1.3643 ],
			"to": [ 8.810619, 23.5, -0.6643001 ],
			"faces": {
				"down": { "uv": [ 7.5, 7, 8, 7.5 ], "texture": "#1_1", "cullface": "down" },
				"up": { "uv": [ 7.5, 7, 8, 7.5 ], "texture": "#1_1", "cullface": "up" },
				"north": { "uv": [ 7.5, 7, 8, 7.5 ], "texture": "#1_1", "cullface": "north" },
				"south": { "uv": [ 7.5, 7, 8, 7.5 ], "texture": "#1_1", "cullface": "south" },
				"west": { "uv": [ 7.5, 7, 8, 7.5 ], "texture": "#1_1", "cullface": "west" },
				"east": { "uv": [ 7.5, 7, 8, 7.5 ], "texture": "#1_1", "cullface": "east" }
			}
		},
		{
			"__comment": "Element",
			"from": [ 7.65, 13.5, 16.175 ],
			"to": [ 8.35, 23.5, 17.79632 ],
			"faces": {
				"down": { "uv": [ 7.5, 7, 8, 7.5 ], "texture": "#1_1", "cullface": "down" },
				"up": { "uv": [ 7.5, 7, 8, 7.5 ], "texture": "#1_1", "cullface": "up" },
				"north": { "uv": [ 7.5, 7, 8, 7.5 ], "texture": "#1_1", "cullface": "north" },
				"south": { "uv": [ 7.5, 7, 8, 7.5 ], "texture": "#1_1", "cullface": "south" },
				"west": { "uv": [ 7.5, 7, 8, 7.5 ], "texture": "#1_1", "cullface": "west" },
				"east": { "uv": [ 7.5, 7, 8, 7.5 ], "texture": "#1_1", "cullface": "east" }
			}
		},
		{
			"__comment": "Element",
			"from": [ 7.6743, 13.5, 16.165 ],
			"to": [ 8.325779, 23.5, 17.80642 ],
			"rotation": { "origin": [ 8, 25, 16.98566 ], "axis": "y", "angle": 45 },
			"faces": {
				"down": { "uv": [ 7.5, 7, 8, 7.5 ], "texture": "#1_1", "cullface": "down" },
				"up": { "uv": [ 7.5, 7, 8, 7.5 ], "texture": "#1_1", "cullface": "up" },
				"north": { "uv": [ 7.5, 7, 8, 7.5 ], "texture": "#1_1", "cullface": "north" },
				"south": { "uv": [ 7.5, 7, 8, 7.5 ], "texture": "#1_1", "cullface": "south" },
				"west": { "uv": [ 7.5, 7, 8, 7.5 ], "texture": "#1_1", "cullface": "west" },
				"east": { "uv": [ 7.5, 7, 8, 7.5 ], "texture": "#1_1", "cullface": "east" }
			}
		},
		{
			"__comment": "Element",
			"from": [ 7.1793, 13.5, 16.6599 ],
			"to": [ 8.820721, 23.5, 17.31138 ],
			"rotation": { "origin": [ 8, 25, 16.98566 ], "axis": "y", "angle": 45 },
			"faces": {
				"down": { "uv": [ 7.5, 7, 8, 7.5 ], "texture": "#1_1", "cullface": "down" },
				"up": { "uv": [ 7.5, 7, 8, 7.5 ], "texture": "#1_1", "cullface": "up" },
				"north": { "uv": [ 7.5, 7, 8, 7.5 ], "texture": "#1_1", "cullface": "north" },
				"south": { "uv": [ 7.5, 7, 8, 7.5 ], "texture": "#1_1", "cullface": "south" },
				"west": { "uv": [ 7.5, 7, 8, 7.5 ], "texture": "#1_1", "cullface": "west" },
				"east": { "uv": [ 7.5, 7, 8, 7.5 ], "texture": "#1_1", "cullface": "east" }
			}
		},
		{
			"__comment": "Element",
			"from": [ 7.1893, 13.5, 16.6357 ],
			"to": [ 8.810619, 23.5, 17.3357 ],
			"faces": {
				"down": { "uv": [ 7.5, 7, 8, 7.5 ], "texture": "#1_1", "cullface": "down" },
				"up": { "uv": [ 7.5, 7, 8, 7.5 ], "texture": "#1_1", "cullface": "up" },
				"north": { "uv": [ 7.5, 7, 8, 7.5 ], "texture": "#1_1", "cullface": "north" },
				"south": { "uv": [ 7.5, 7, 8, 7.5 ], "texture": "#1_1", "cullface": "south" },
				"west": { "uv": [ 7.5, 7, 8, 7.5 ], "texture": "#1_1", "cullface": "west" },
				"east": { "uv": [ 7.5, 7, 8, 7.5 ], "texture": "#1_1", "cullface": "east" }
			}
		},
		{
			"__comment": "Element",
			"from": [ 8.849999, 27.4498, 7.85 ],
			"to": [ 9.099999, 28.1998, 8.1 ],
			"faces": {
				"down": { "uv": [ 8, 6.5, 8.5, 7 ], "texture": "#1_1", "cullface": "down" },
				"up": { "uv": [ 8, 6.5, 8.5, 7 ], "texture": "#1_1", "cullface": "up" },
				"north": { "uv": [ 8, 6.5, 8.5, 7 ], "texture": "#1_1", "cullface": "north" },
				"south": { "uv": [ 8, 6.5, 8.5, 7 ], "texture": "#1_1", "cullface": "south" },
				"west": { "uv": [ 8, 6.5, 8.5, 7 ], "texture": "#1_1", "cullface": "west" },
				"east": { "uv": [ 8, 6.5, 8.5, 7 ], "texture": "#1_1", "cullface": "east" }
			}
		},
		{
			"__comment": "Element",
			"from": [ 6.85, 27.4498, 7.85 ],
			"to": [ 7.1, 28.1998, 8.1 ],
			"faces": {
				"down": { "uv": [ 8.5, 6.5, 8, 7 ], "texture": "#1_1", "cullface": "down" },
				"up": { "uv": [ 8.5, 6.5, 8, 7 ], "texture": "#1_1", "cullface": "up" },
				"north": { "uv": [ 8.5, 6.5, 8, 7 ], "texture": "#1_1", "cullface": "north" },
				"south": { "uv": [ 8.5, 6.5, 8, 7 ], "texture": "#1_1", "cullface": "south" },
				"west": { "uv": [ 8.5, 6.5, 8, 7 ], "texture": "#1_1", "cullface": "west" },
				"east": { "uv": [ 8.5, 6.5, 8, 7 ], "texture": "#1_1", "cullface": "east" }
			}
		},
		{
			"__comment": "Element",
			"from": [ 8.05, 29.4498, 7.85 ],
			"to": [ 8.3, 30.1998, 8.1 ],
			"faces": {
				"down": { "uv": [ 8, 6.5, 8.5, 7 ], "texture": "#1_1", "cullface": "down" },
				"up": { "uv": [ 8, 6.5, 8.5, 7 ], "texture": "#1_1", "cullface": "up" },
				"north": { "uv": [ 8, 6.5, 8.5, 7 ], "texture": "#1_1", "cullface": "north" },
				"south": { "uv": [ 8, 6.5, 8.5, 7 ], "texture": "#1_1", "cullface": "south" },
				"west": { "uv": [ 8, 6.5, 8.5, 7 ], "texture": "#1_1", "cullface": "west" },
				"east": { "uv": [ 8, 6.5, 8.5, 7 ], "texture": "#1_1", "cullface": "east" }
			}
		},
		{
			"__comment": "Element",
			"from": [ 7.65, 29.4498, 7.85 ],
			"to": [ 7.9, 30.1998, 8.1 ],
			"faces": {
				"down": { "uv": [ 8.5, 6.5, 8, 7 ], "texture": "#1_1", "cullface": "down" },
				"up": { "uv": [ 8.5, 6.5, 8, 7 ], "texture": "#1_1", "cullface": "up" },
				"north": { "uv": [ 8.5, 6.5, 8, 7 ], "texture": "#1_1", "cullface": "north" },
				"south": { "uv": [ 8.5, 6.5, 8, 7 ], "texture": "#1_1", "cullface": "south" },
				"west": { "uv": [ 8.5, 6.5, 8, 7 ], "texture": "#1_1", "cullface": "west" },
				"east": { "uv": [ 8.5, 6.5, 8, 7 ], "texture": "#1_1", "cullface": "east" }
			}
		},
		{
			"__comment": "Element",
			"from": [ 8.25, 28.9498, 7.85 ],
			"to": [ 8.5, 29.6998, 8.1 ],
			"faces": {
				"down": { "uv": [ 8, 6.5, 8.5, 7 ], "texture": "#1_1", "cullface": "down" },
				"up": { "uv": [ 8, 6.5, 8.5, 7 ], "texture": "#1_1", "cullface": "up" },
				"north": { "uv": [ 8, 6.5, 8.5, 7 ], "texture": "#1_1", "cullface": "north" },
				"south": { "uv": [ 8, 6.5, 8.5, 7 ], "texture": "#1_1", "cullface": "south" },
				"west": { "uv": [ 8, 6.5, 8.5, 7 ], "texture": "#1_1", "cullface": "west" },
				"east": { "uv": [ 8, 6.5, 8.5, 7 ], "texture": "#1_1", "cullface": "east" }
			}
		},
		{
			"__comment": "Element",
			"from": [ 7.45, 28.9498, 7.85 ],
			"to": [ 7.7, 29.6998, 8.1 ],
			"faces": {
				"down": { "uv": [ 8.5, 6.5, 8, 7 ], "texture": "#1_1", "cullface": "down" },
				"up": { "uv": [ 8.5, 6.5, 8, 7 ], "texture": "#1_1", "cullface": "up" },
				"north": { "uv": [ 8.5, 6.5, 8, 7 ], "texture": "#1_1", "cullface": "north" },
				"south": { "uv": [ 8.5, 6.5, 8, 7 ], "texture": "#1_1", "cullface": "south" },
				"west": { "uv": [ 8.5, 6.5, 8, 7 ], "texture": "#1_1", "cullface": "west" },
				"east": { "uv": [ 8.5, 6.5, 8, 7 ], "texture": "#1_1", "cullface": "east" }
			}
		},
		{
			"__comment": "Element",
			"from": [ 8.45, 28.4498, 7.85 ],
			"to": [ 8.7, 29.1998, 8.1 ],
			"faces": {
				"down": { "uv": [ 8, 6.5, 8.5, 7 ], "texture": "#1_1", "cullface": "down" },
				"up": { "uv": [ 8, 6.5, 8.5, 7 ], "texture": "#1_1", "cullface": "up" },
				"north": { "uv": [ 8, 6.5, 8.5, 7 ], "texture": "#1_1", "cullface": "north" },
				"south": { "uv": [ 8, 6.5, 8.5, 7 ], "texture": "#1_1", "cullface": "south" },
				"west": { "uv": [ 8, 6.5, 8.5, 7 ], "texture": "#1_1", "cullface": "west" },
				"east": { "uv": [ 8, 6.5, 8.5, 7 ], "texture": "#1_1", "cullface": "east" }
			}
		},
		{
			"__comment": "Element",
			"from": [ 7.25, 28.4498, 7.85 ],
			"to": [ 7.5, 29.1998, 8.1 ],
			"faces": {
				"down": { "uv": [ 8.5, 6.5, 8, 7 ], "texture": "#1_1", "cullface": "down" },
				"up": { "uv": [ 8.5, 6.5, 8, 7 ], "texture": "#1_1", "cullface": "up" },
				"north": { "uv": [ 8.5, 6.5, 8, 7 ], "texture": "#1_1", "cullface": "north" },
				"south": { "uv": [ 8.5, 6.5, 8, 7 ], "texture": "#1_1", "cullface": "south" },
				"west": { "uv": [ 8.5, 6.5, 8, 7 ], "texture": "#1_1", "cullface": "west" },
				"east": { "uv": [ 8.5, 6.5, 8, 7 ], "texture": "#1_1", "cullface": "east" }
			}
		},
		{
			"__comment": "Element",
			"from": [ 8.65, 27.9498, 7.85 ],
			"to": [ 8.9, 28.6998, 8.1 ],
			"faces": {
				"down": { "uv": [ 8, 6.5, 8.5, 7 ], "texture": "#1_1", "cullface": "down" },
				"up": { "uv": [ 8, 6.5, 8.5, 7 ], "texture": "#1_1", "cullface": "up" },
				"north": { "uv": [ 8, 6.5, 8.5, 7 ], "texture": "#1_1", "cullface": "north" },
				"south": { "uv": [ 8, 6.5, 8.5, 7 ], "texture": "#1_1", "cullface": "south" },
				"west": { "uv": [ 8, 6.5, 8.5, 7 ], "texture": "#1_1", "cullface": "west" },
				"east": { "uv": [ 8, 6.5, 8.5, 7 ], "texture": "#1_1", "cullface": "east" }
			}
		},
		{
			"__comment": "Element",
			"from": [ 7.05, 27.9498, 7.85 ],
			"to": [ 7.3, 28.6998, 8.1 ],
			"faces": {
				"down": { "uv": [ 8.5, 6.5, 8, 7 ], "texture": "#1_1", "cullface": "down" },
				"up": { "uv": [ 8.5, 6.5, 8, 7 ], "texture": "#1_1", "cullface": "up" },
				"north": { "uv": [ 8.5, 6.5, 8, 7 ], "texture": "#1_1", "cullface": "north" },
				"south": { "uv": [ 8.5, 6.5, 8, 7 ], "texture": "#1_1", "cullface": "south" },
				"west": { "uv": [ 8.5, 6.5, 8, 7 ], "texture": "#1_1", "cullface": "west" },
				"east": { "uv": [ 8.5, 6.5, 8, 7 ], "texture": "#1_1", "cullface": "east" }
			}
		},
		{
			"__comment": "Element",
			"from": [ 9.05, 26.9498, 7.85 ],
			"to": [ 9.3, 27.6998, 8.1 ],
			"faces": {
				"down": { "uv": [ 8, 6.5, 8.5, 7 ], "texture": "#1_1", "cullface": "down" },
				"up": { "uv": [ 8, 6.5, 8.5, 7 ], "texture": "#1_1", "cullface": "up" },
				"north": { "uv": [ 8, 6.5, 8.5, 7 ], "texture": "#1_1", "cullface": "north" },
				"south": { "uv": [ 8, 6.5, 8.5, 7 ], "texture": "#1_1", "cullface": "south" },
				"west": { "uv": [ 8, 6.5, 8.5, 7 ], "texture": "#1_1", "cullface": "west" },
				"east": { "uv": [ 8, 6.5, 8.5, 7 ], "texture": "#1_1", "cullface": "east" }
			}
		},
		{
			"__comment": "Element",
			"from": [ 6.65, 26.9498, 7.85 ],
			"to": [ 6.9, 27.6998, 8.1 ],
			"faces": {
				"down": { "uv": [ 8.5, 6.5, 8, 7 ], "texture": "#1_1", "cullface": "down" },
				"up": { "uv": [ 8.5, 6.5, 8, 7 ], "texture": "#1_1", "cullface": "up" },
				"north": { "uv": [ 8.5, 6.5, 8, 7 ], "texture": "#1_1", "cullface": "north" },
				"south": { "uv": [ 8.5, 6.5, 8, 7 ], "texture": "#1_1", "cullface": "south" },
				"west": { "uv": [ 8.5, 6.5, 8, 7 ], "texture": "#1_1", "cullface": "west" },
				"east": { "uv": [ 8.5, 6.5, 8, 7 ], "texture": "#1_1", "cullface": "east" }
			}
		},
		{
			"__comment": "Element",
			"from": [ 9.25, 26.4498, 7.85 ],
			"to": [ 9.5, 27.1998, 8.1 ],
			"faces": {
				"down": { "uv": [ 8, 6.5, 8.5, 7 ], "texture": "#1_1", "cullface": "down" },
				"up": { "uv": [ 8, 6.5, 8.5, 7 ], "texture": "#1_1", "cullface": "up" },
				"north": { "uv": [ 8, 6.5, 8.5, 7 ], "texture": "#1_1", "cullface": "north" },
				"south": { "uv": [ 8, 6.5, 8.5, 7 ], "texture": "#1_1", "cullface": "south" },
				"west": { "uv": [ 8, 6.5, 8.5, 7 ], "texture": "#1_1", "cullface": "west" },
				"east": { "uv": [ 8, 6.5, 8.5, 7 ], "texture": "#1_1", "cullface": "east" }
			}
		},
		{
			"__comment": "Element",
			"from": [ 6.45, 26.4498, 7.85 ],
			"to": [ 6.7, 27.1998, 8.1 ],
			"faces": {
				"down": { "uv": [ 8.5, 6.5, 8, 7 ], "texture": "#1_1", "cullface": "down" },
				"up": { "uv": [ 8.5, 6.5, 8, 7 ], "texture": "#1_1", "cullface": "up" },
				"north": { "uv": [ 8.5, 6.5, 8, 7 ], "texture": "#1_1", "cullface": "north" },
				"south": { "uv": [ 8.5, 6.5, 8, 7 ], "texture": "#1_1", "cullface": "south" },
				"west": { "uv": [ 8.5, 6.5, 8, 7 ], "texture": "#1_1", "cullface": "west" },
				"east": { "uv": [ 8.5, 6.5, 8, 7 ], "texture": "#1_1", "cullface": "east" }
			}
		},
		{
			"__comment": "Element",
			"from": [ 7.85, 29.9498, 7.85 ],
			"to": [ 8.1, 30.6998, 8.1 ],
			"faces": {
				"down": { "uv": [ 8, 6.5, 8.5, 7 ], "texture": "#1_1", "cullface": "down" },
				"up": { "uv": [ 8, 6.5, 8.5, 7 ], "texture": "#1_1", "cullface": "up" },
				"north": { "uv": [ 8, 6.5, 8.5, 7 ], "texture": "#1_1", "cullface": "north" },
				"south": { "uv": [ 8, 6.5, 8.5, 7 ], "texture": "#1_1", "cullface": "south" },
				"west": { "uv": [ 8, 6.5, 8.5, 7 ], "texture": "#1_1", "cullface": "west" },
				"east": { "uv": [ 8, 6.5, 8.5, 7 ], "texture": "#1_1", "cullface": "east" }
			}
		},
		{
			"__comment": "Element",
			"from": [ 7.85, 28.7998, 11.35 ],
			"to": [ 8.1, 29.5498, 11.6 ],
			"faces": {
				"down": { "uv": [ 8, 6.5, 8.5, 7 ], "texture": "#1_1", "cullface": "down" },
				"up": { "uv": [ 8, 6.5, 8.5, 7 ], "texture": "#1_1", "cullface": "up" },
				"north": { "uv": [ 8, 6.5, 8.5, 7 ], "texture": "#1_1", "cullface": "north" },
				"south": { "uv": [ 8, 6.5, 8.5, 7 ], "texture": "#1_1", "cullface": "south" },
				"west": { "uv": [ 8, 6.5, 8.5, 7 ], "texture": "#1_1", "cullface": "west" },
				"east": { "uv": [ 8, 6.5, 8.5, 7 ], "texture": "#1_1", "cullface": "east" }
			}
		},
		{
			"__comment": "Element",
			"from": [ 6.65, 25.7998, 11.35 ],
			"to": [ 6.9, 26.5498, 11.6 ],
			"faces": {
				"down": { "uv": [ 8.5, 6.5, 8, 7 ], "texture": "#1_1", "cullface": "down" },
				"up": { "uv": [ 8.5, 6.5, 8, 7 ], "texture": "#1_1", "cullface": "up" },
				"north": { "uv": [ 8.5, 6.5, 8, 7 ], "texture": "#1_1", "cullface": "north" },
				"south": { "uv": [ 8.5, 6.5, 8, 7 ], "texture": "#1_1", "cullface": "south" },
				"west": { "uv": [ 8.5, 6.5, 8, 7 ], "texture": "#1_1", "cullface": "west" },
				"east": { "uv": [ 8.5, 6.5, 8, 7 ], "texture": "#1_1", "cullface": "east" }
			}
		},
		{
			"__comment": "Element",
			"from": [ 9.05, 25.7998, 11.35 ],
			"to": [ 9.3, 26.5498, 11.6 ],
			"faces": {
				"down": { "uv": [ 8, 6.5, 8.5, 7 ], "texture": "#1_1", "cullface": "down" },
				"up": { "uv": [ 8, 6.5, 8.5, 7 ], "texture": "#1_1", "cullface": "up" },
				"north": { "uv": [ 8, 6.5, 8.5, 7 ], "texture": "#1_1", "cullface": "north" },
				"south": { "uv": [ 8, 6.5, 8.5, 7 ], "texture": "#1_1", "cullface": "south" },
				"west": { "uv": [ 8, 6.5, 8.5, 7 ], "texture": "#1_1", "cullface": "west" },
				"east": { "uv": [ 8, 6.5, 8.5, 7 ], "texture": "#1_1", "cullface": "east" }
			}
		},
		{
			"__comment": "Element",
			"from": [ 7.05, 26.7998, 11.35 ],
			"to": [ 7.3, 27.5498, 11.6 ],
			"faces": {
				"down": { "uv": [ 8.5, 6.5, 8, 7 ], "texture": "#1_1", "cullface": "down" },
				"up": { "uv": [ 8.5, 6.5, 8, 7 ], "texture": "#1_1", "cullface": "up" },
				"north": { "uv": [ 8.5, 6.5, 8, 7 ], "texture": "#1_1", "cullface": "north" },
				"south": { "uv": [ 8.5, 6.5, 8, 7 ], "texture": "#1_1", "cullface": "south" },
				"west": { "uv": [ 8.5, 6.5, 8, 7 ], "texture": "#1_1", "cullface": "west" },
				"east": { "uv": [ 8.5, 6.5, 8, 7 ], "texture": "#1_1", "cullface": "east" }
			}
		},
		{
			"__comment": "Element",
			"from": [ 8.65, 26.7998, 11.35 ],
			"to": [ 8.9, 27.5498, 11.6 ],
			"faces": {
				"down": { "uv": [ 8, 6.5, 8.5, 7 ], "texture": "#1_1", "cullface": "down" },
				"up": { "uv": [ 8, 6.5, 8.5, 7 ], "texture": "#1_1", "cullface": "up" },
				"north": { "uv": [ 8, 6.5, 8.5, 7 ], "texture": "#1_1", "cullface": "north" },
				"south": { "uv": [ 8, 6.5, 8.5, 7 ], "texture": "#1_1", "cullface": "south" },
				"west": { "uv": [ 8, 6.5, 8.5, 7 ], "texture": "#1_1", "cullface": "west" },
				"east": { "uv": [ 8, 6.5, 8.5, 7 ], "texture": "#1_1", "cullface": "east" }
			}
		},
		{
			"__comment": "Element",
			"from": [ 7.25, 27.2998, 11.35 ],
			"to": [ 7.5, 28.0498, 11.6 ],
			"faces": {
				"down": { "uv": [ 8.5, 6.5, 8, 7 ], "texture": "#1_1", "cullface": "down" },
				"up": { "uv": [ 8.5, 6.5, 8, 7 ], "texture": "#1_1", "cullface": "up" },
				"north": { "uv": [ 8.5, 6.5, 8, 7 ], "texture": "#1_1", "cullface": "north" },
				"south": { "uv": [ 8.5, 6.5, 8, 7 ], "texture": "#1_1", "cullface": "south" },
				"west": { "uv": [ 8.5, 6.5, 8, 7 ], "texture": "#1_1", "cullface": "west" },
				"east": { "uv": [ 8.5, 6.5, 8, 7 ], "texture": "#1_1", "cullface": "east" }
			}
		},
		{
			"__comment": "Element",
			"from": [ 8.45, 27.2998, 11.35 ],
			"to": [ 8.7, 28.0498, 11.6 ],
			"faces": {
				"down": { "uv": [ 8, 6.5, 8.5, 7 ], "texture": "#1_1", "cullface": "down" },
				"up": { "uv": [ 8, 6.5, 8.5, 7 ], "texture": "#1_1", "cullface": "up" },
				"north": { "uv": [ 8, 6.5, 8.5, 7 ], "texture": "#1_1", "cullface": "north" },
				"south": { "uv": [ 8, 6.5, 8.5, 7 ], "texture": "#1_1", "cullface": "south" },
				"west": { "uv": [ 8, 6.5, 8.5, 7 ], "texture": "#1_1", "cullface": "west" },
				"east": { "uv": [ 8, 6.5, 8.5, 7 ], "texture": "#1_1", "cullface": "east" }
			}
		},
		{
			"__comment": "Element",
			"from": [ 7.45, 27.7998, 11.35 ],
			"to": [ 7.7, 28.5498, 11.6 ],
			"faces": {
				"down": { "uv": [ 8.5, 6.5, 8, 7 ], "texture": "#1_1", "cullface": "down" },
				"up": { "uv": [ 8.5, 6.5, 8, 7 ], "texture": "#1_1", "cullface": "up" },
				"north": { "uv": [ 8.5, 6.5, 8, 7 ], "texture": "#1_1", "cullface": "north" },
				"south": { "uv": [ 8.5, 6.5, 8, 7 ], "texture": "#1_1", "cullface": "south" },
				"west": { "uv": [ 8.5, 6.5, 8, 7 ], "texture": "#1_1", "cullface": "west" },
				"east": { "uv": [ 8.5, 6.5, 8, 7 ], "texture": "#1_1", "cullface": "east" }
			}
		},
		{
			"__comment": "Element",
			"from": [ 8.25, 27.7998, 11.35 ],
			"to": [ 8.5, 28.5498, 11.6 ],
			"faces": {
				"down": { "uv": [ 8, 6.5, 8.5, 7 ], "texture": "#1_1", "cullface": "down" },
				"up": { "uv": [ 8, 6.5, 8.5, 7 ], "texture": "#1_1", "cullface": "up" },
				"north": { "uv": [ 8, 6.5, 8.5, 7 ], "texture": "#1_1", "cullface": "north" },
				"south": { "uv": [ 8, 6.5, 8.5, 7 ], "texture": "#1_1", "cullface": "south" },
				"west": { "uv": [ 8, 6.5, 8.5, 7 ], "texture": "#1_1", "cullface": "west" },
				"east": { "uv": [ 8, 6.5, 8.5, 7 ], "texture": "#1_1", "cullface": "east" }
			}
		},
		{
			"__comment": "Element",
			"from": [ 7.65, 28.2998, 11.35 ],
			"to": [ 7.9, 29.0498, 11.6 ],
			"faces": {
				"down": { "uv": [ 8.5, 6.5, 8, 7 ], "texture": "#1_1", "cullface": "down" },
				"up": { "uv": [ 8.5, 6.5, 8, 7 ], "texture": "#1_1", "cullface": "up" },
				"north": { "uv": [ 8.5, 6.5, 8, 7 ], "texture": "#1_1", "cullface": "north" },
				"south": { "uv": [ 8.5, 6.5, 8, 7 ], "texture": "#1_1", "cullface": "south" },
				"west": { "uv": [ 8.5, 6.5, 8, 7 ], "texture": "#1_1", "cullface": "west" },
				"east": { "uv": [ 8.5, 6.5, 8, 7 ], "texture": "#1_1", "cullface": "east" }
			}
		},
		{
			"__comment": "Element",
			"from": [ 8.05, 28.2998, 11.35 ],
			"to": [ 8.3, 29.0498, 11.6 ],
			"faces": {
				"down": { "uv": [ 8, 6.5, 8.5, 7 ], "texture": "#1_1", "cullface": "down" },
				"up": { "uv": [ 8, 6.5, 8.5, 7 ], "texture": "#1_1", "cullface": "up" },
				"north": { "uv": [ 8, 6.5, 8.5, 7 ], "texture": "#1_1", "cullface": "north" },
				"south": { "uv": [ 8, 6.5, 8.5, 7 ], "texture": "#1_1", "cullface": "south" },
				"west": { "uv": [ 8, 6.5, 8.5, 7 ], "texture": "#1_1", "cullface": "west" },
				"east": { "uv": [ 8, 6.5, 8.5, 7 ], "texture": "#1_1", "cullface": "east" }
			}
		},
		{
			"__comment": "Element",
			"from": [ 6.85, 26.2998, 11.35 ],
			"to": [ 7.1, 27.0498, 11.6 ],
			"faces": {
				"down": { "uv": [ 8.5, 6.5, 8, 7 ], "texture": "#1_1", "cullface": "down" },
				"up": { "uv": [ 8.5, 6.5, 8, 7 ], "texture": "#1_1", "cullface": "up" },
				"north": { "uv": [ 8.5, 6.5, 8, 7 ], "texture": "#1_1", "cullface": "north" },
				"south": { "uv": [ 8.5, 6.5, 8, 7 ], "texture": "#1_1", "cullface": "south" },
				"west": { "uv": [ 8.5, 6.5, 8, 7 ], "texture": "#1_1", "cullface": "west" },
				"east": { "uv": [ 8.5, 6.5, 8, 7 ], "texture": "#1_1", "cullface": "east" }
			}
		},
		{
			"__comment": "Element",
			"from": [ 8.849999, 26.2998, 11.35 ],
			"to": [ 9.099999, 27.0498, 11.6 ],
			"faces": {
				"down": { "uv": [ 8, 6.5, 8.5, 7 ], "texture": "#1_1", "cullface": "down" },
				"up": { "uv": [ 8, 6.5, 8.5, 7 ], "texture": "#1_1", "cullface": "up" },
				"north": { "uv": [ 8, 6.5, 8.5, 7 ], "texture": "#1_1", "cullface": "north" },
				"south": { "uv": [ 8, 6.5, 8.5, 7 ], "texture": "#1_1", "cullface": "south" },
				"west": { "uv": [ 8, 6.5, 8.5, 7 ], "texture": "#1_1", "cullface": "west" },
				"east": { "uv": [ 8, 6.5, 8.5, 7 ], "texture": "#1_1", "cullface": "east" }
			}
		},
		{
			"__comment": "Element",
			"from": [ 7.85, 28.7998, 4.35 ],
			"to": [ 8.1, 29.5498, 4.6 ],
			"faces": {
				"down": { "uv": [ 8, 6.5, 8.5, 7 ], "texture": "#1_1", "cullface": "down" },
				"up": { "uv": [ 8, 6.5, 8.5, 7 ], "texture": "#1_1", "cullface": "up" },
				"north": { "uv": [ 8, 6.5, 8.5, 7 ], "texture": "#1_1", "cullface": "north" },
				"south": { "uv": [ 8, 6.5, 8.5, 7 ], "texture": "#1_1", "cullface": "south" },
				"west": { "uv": [ 8, 6.5, 8.5, 7 ], "texture": "#1_1", "cullface": "west" },
				"east": { "uv": [ 8, 6.5, 8.5, 7 ], "texture": "#1_1", "cullface": "east" }
			}
		},
		{
			"__comment": "Element",
			"from": [ 6.65, 25.7998, 4.35 ],
			"to": [ 6.9, 26.5498, 4.6 ],
			"faces": {
				"down": { "uv": [ 8.5, 6.5, 8, 7 ], "texture": "#1_1", "cullface": "down" },
				"up": { "uv": [ 8.5, 6.5, 8, 7 ], "texture": "#1_1", "cullface": "up" },
				"north": { "uv": [ 8.5, 6.5, 8, 7 ], "texture": "#1_1", "cullface": "north" },
				"south": { "uv": [ 8.5, 6.5, 8, 7 ], "texture": "#1_1", "cullface": "south" },
				"west": { "uv": [ 8.5, 6.5, 8, 7 ], "texture": "#1_1", "cullface": "west" },
				"east": { "uv": [ 8.5, 6.5, 8, 7 ], "texture": "#1_1", "cullface": "east" }
			}
		},
		{
			"__comment": "Element",
			"from": [ 9.05, 25.7998, 4.35 ],
			"to": [ 9.3, 26.5498, 4.6 ],
			"faces": {
				"down": { "uv": [ 8, 6.5, 8.5, 7 ], "texture": "#1_1", "cullface": "down" },
				"up": { "uv": [ 8, 6.5, 8.5, 7 ], "texture": "#1_1", "cullface": "up" },
				"north": { "uv": [ 8, 6.5, 8.5, 7 ], "texture": "#1_1", "cullface": "north" },
				"south": { "uv": [ 8, 6.5, 8.5, 7 ], "texture": "#1_1", "cullface": "south" },
				"west": { "uv": [ 8, 6.5, 8.5, 7 ], "texture": "#1_1", "cullface": "west" },
				"east": { "uv": [ 8, 6.5, 8.5, 7 ], "texture": "#1_1", "cullface": "east" }
			}
		},
		{
			"__comment": "Element",
			"from": [ 7.05, 26.7998, 4.35 ],
			"to": [ 7.3, 27.5498, 4.6 ],
			"faces": {
				"down": { "uv": [ 8.5, 6.5, 8, 7 ], "texture": "#1_1", "cullface": "down" },
				"up": { "uv": [ 8.5, 6.5, 8, 7 ], "texture": "#1_1", "cullface": "up" },
				"north": { "uv": [ 8.5, 6.5, 8, 7 ], "texture": "#1_1", "cullface": "north" },
				"south": { "uv": [ 8.5, 6.5, 8, 7 ], "texture": "#1_1", "cullface": "south" },
				"west": { "uv": [ 8.5, 6.5, 8, 7 ], "texture": "#1_1", "cullface": "west" },
				"east": { "uv": [ 8.5, 6.5, 8, 7 ], "texture": "#1_1", "cullface": "east" }
			}
		},
		{
			"__comment": "Element",
			"from": [ 8.65, 26.7998, 4.35 ],
			"to": [ 8.9, 27.5498, 4.6 ],
			"faces": {
				"down": { "uv": [ 8, 6.5, 8.5, 7 ], "texture": "#1_1", "cullface": "down" },
				"up": { "uv": [ 8, 6.5, 8.5, 7 ], "texture": "#1_1", "cullface": "up" },
				"north": { "uv": [ 8, 6.5, 8.5, 7 ], "texture": "#1_1", "cullface": "north" },
				"south": { "uv": [ 8, 6.5, 8.5, 7 ], "texture": "#1_1", "cullface": "south" },
				"west": { "uv": [ 8, 6.5, 8.5, 7 ], "texture": "#1_1", "cullface": "west" },
				"east": { "uv": [ 8, 6.5, 8.5, 7 ], "texture": "#1_1", "cullface": "east" }
			}
		},
		{
			"__comment": "Element",
			"from": [ 7.25, 27.2998, 4.35 ],
			"to": [ 7.5, 28.0498, 4.6 ],
			"faces": {
				"down": { "uv": [ 8.5, 6.5, 8, 7 ], "texture": "#1_1", "cullface": "down" },
				"up": { "uv": [ 8.5, 6.5, 8, 7 ], "texture": "#1_1", "cullface": "up" },
				"north": { "uv": [ 8.5, 6.5, 8, 7 ], "texture": "#1_1", "cullface": "north" },
				"south": { "uv": [ 8.5, 6.5, 8, 7 ], "texture": "#1_1", "cullface": "south" },
				"west": { "uv": [ 8.5, 6.5, 8, 7 ], "texture": "#1_1", "cullface": "west" },
				"east": { "uv": [ 8.5, 6.5, 8, 7 ], "texture": "#1_1", "cullface": "east" }
			}
		},
		{
			"__comment": "Element",
			"from": [ 8.45, 27.2998, 4.35 ],
			"to": [ 8.7, 28.0498, 4.6 ],
			"faces": {
				"down": { "uv": [ 8, 6.5, 8.5, 7 ], "texture": "#1_1", "cullface": "down" },
				"up": { "uv": [ 8, 6.5, 8.5, 7 ], "texture": "#1_1", "cullface": "up" },
				"north": { "uv": [ 8, 6.5, 8.5, 7 ], "texture": "#1_1", "cullface": "north" },
				"south": { "uv": [ 8, 6.5, 8.5, 7 ], "texture": "#1_1", "cullface": "south" },
				"west": { "uv": [ 8, 6.5, 8.5, 7 ], "texture": "#1_1", "cullface": "west" },
				"east": { "uv": [ 8, 6.5, 8.5, 7 ], "texture": "#1_1", "cullface": "east" }
			}
		},
		{
			"__comment": "Element",
			"from": [ 7.45, 27.7998, 4.35 ],
			"to": [ 7.7, 28.5498, 4.6 ],
			"faces": {
				"down": { "uv": [ 8.5, 6.5, 8, 7 ], "texture": "#1_1", "cullface": "down" },
				"up": { "uv": [ 8.5, 6.5, 8, 7 ], "texture": "#1_1", "cullface": "up" },
				"north": { "uv": [ 8.5, 6.5, 8, 7 ], "texture": "#1_1", "cullface": "north" },
				"south": { "uv": [ 8.5, 6.5, 8, 7 ], "texture": "#1_1", "cullface": "south" },
				"west": { "uv": [ 8.5, 6.5, 8, 7 ], "texture": "#1_1", "cullface": "west" },
				"east": { "uv": [ 8.5, 6.5, 8, 7 ], "texture": "#1_1", "cullface": "east" }
			}
		},
		{
			"__comment": "Element",
			"from": [ 8.25, 27.7998, 4.35 ],
			"to": [ 8.5, 28.5498, 4.6 ],
			"faces": {
				"down": { "uv": [ 8, 6.5, 8.5, 7 ], "texture": "#1_1", "cullface": "down" },
				"up": { "uv": [ 8, 6.5, 8.5, 7 ], "texture": "#1_1", "cullface": "up" },
				"north": { "uv": [ 8, 6.5, 8.5, 7 ], "texture": "#1_1", "cullface": "north" },
				"south": { "uv": [ 8, 6.5, 8.5, 7 ], "texture": "#1_1", "cullface": "south" },
				"west": { "uv": [ 8, 6.5, 8.5, 7 ], "texture": "#1_1", "cullface": "west" },
				"east": { "uv": [ 8, 6.5, 8.5, 7 ], "texture": "#1_1", "cullface": "east" }
			}
		},
		{
			"__comment": "Element",
			"from": [ 7.65, 28.2998, 4.35 ],
			"to": [ 7.9, 29.0498, 4.6 ],
			"faces": {
				"down": { "uv": [ 8.5, 6.5, 8, 7 ], "texture": "#1_1", "cullface": "down" },
				"up": { "uv": [ 8.5, 6.5, 8, 7 ], "texture": "#1_1", "cullface": "up" },
				"north": { "uv": [ 8.5, 6.5, 8, 7 ], "texture": "#1_1", "cullface": "north" },
				"south": { "uv": [ 8.5, 6.5, 8, 7 ], "texture": "#1_1", "cullface": "south" },
				"west": { "uv": [ 8.5, 6.5, 8, 7 ], "texture": "#1_1", "cullface": "west" },
				"east": { "uv": [ 8.5, 6.5, 8, 7 ], "texture": "#1_1", "cullface": "east" }
			}
		},
		{
			"__comment": "Element",
			"from": [ 8.05, 28.2998, 4.35 ],
			"to": [ 8.3, 29.0498, 4.6 ],
			"faces": {
				"down": { "uv": [ 8, 6.5, 8.5, 7 ], "texture": "#1_1", "cullface": "down" },
				"up": { "uv": [ 8, 6.5, 8.5, 7 ], "texture": "#1_1", "cullface": "up" },
				"north": { "uv": [ 8, 6.5, 8.5, 7 ], "texture": "#1_1", "cullface": "north" },
				"south": { "uv": [ 8, 6.5, 8.5, 7 ], "texture": "#1_1", "cullface": "south" },
				"west": { "uv": [ 8, 6.5, 8.5, 7 ], "texture": "#1_1", "cullface": "west" },
				"east": { "uv": [ 8, 6.5, 8.5, 7 ], "texture": "#1_1", "cullface": "east" }
			}
		},
		{
			"__comment": "Element",
			"from": [ 6.85, 26.2998, 4.35 ],
			"to": [ 7.1, 27.0498, 4.6 ],
			"faces": {
				"down": { "uv": [ 8.5, 6.5, 8, 7 ], "texture": "#1_1", "cullface": "down" },
				"up": { "uv": [ 8.5, 6.5, 8, 7 ], "texture": "#1_1", "cullface": "up" },
				"north": { "uv": [ 8.5, 6.5, 8, 7 ], "texture": "#1_1", "cullface": "north" },
				"south": { "uv": [ 8.5, 6.5, 8, 7 ], "texture": "#1_1", "cullface": "south" },
				"west": { "uv": [ 8.5, 6.5, 8, 7 ], "texture": "#1_1", "cullface": "west" },
				"east": { "uv": [ 8.5, 6.5, 8, 7 ], "texture": "#1_1", "cullface": "east" }
			}
		},
		{
			"__comment": "Element",
			"from": [ 8.849999, 26.2998, 4.35 ],
			"to": [ 9.099999, 27.0498, 4.6 ],
			"faces": {
				"down": { "uv": [ 8, 6.5, 8.5, 7 ], "texture": "#1_1", "cullface": "down" },
				"up": { "uv": [ 8, 6.5, 8.5, 7 ], "texture": "#1_1", "cullface": "up" },
				"north": { "uv": [ 8, 6.5, 8.5, 7 ], "texture": "#1_1", "cullface": "north" },
				"south": { "uv": [ 8, 6.5, 8.5, 7 ], "texture": "#1_1", "cullface": "south" },
				"west": { "uv": [ 8, 6.5, 8.5, 7 ], "texture": "#1_1", "cullface": "west" },
				"east": { "uv": [ 8, 6.5, 8.5, 7 ], "texture": "#1_1", "cullface": "east" }
			}
		},
		{
			"__comment": "Element",
			"from": [ 7.85, 26.4498, 1.35 ],
			"to": [ 8.1, 27.1998, 1.6 ],
			"faces": {
				"down": { "uv": [ 8, 6.5, 8.5, 7 ], "texture": "#1_1", "cullface": "down" },
				"up": { "uv": [ 8, 6.5, 8.5, 7 ], "texture": "#1_1", "cullface": "up" },
				"north": { "uv": [ 8, 6.5, 8.5, 7 ], "texture": "#1_1", "cullface": "north" },
				"south": { "uv": [ 8, 6.5, 8.5, 7 ], "texture": "#1_1", "cullface": "south" },
				"west": { "uv": [ 8, 6.5, 8.5, 7 ], "texture": "#1_1", "cullface": "west" },
				"east": { "uv": [ 8, 6.5, 8.5, 7 ], "texture": "#1_1", "cullface": "east" }
			}
		},
		{
			"__comment": "Element",
			"from": [ 7.05, 24.4498, 1.35 ],
			"to": [ 7.3, 25.1998, 1.6 ],
			"faces": {
				"down": { "uv": [ 8.5, 6.5, 8, 7 ], "texture": "#1_1", "cullface": "down" },
				"up": { "uv": [ 8.5, 6.5, 8, 7 ], "texture": "#1_1", "cullface": "up" },
				"north": { "uv": [ 8.5, 6.5, 8, 7 ], "texture": "#1_1", "cullface": "north" },
				"south": { "uv": [ 8.5, 6.5, 8, 7 ], "texture": "#1_1", "cullface": "south" },
				"west": { "uv": [ 8.5, 6.5, 8, 7 ], "texture": "#1_1", "cullface": "west" },
				"east": { "uv": [ 8.5, 6.5, 8, 7 ], "texture": "#1_1", "cullface": "east" }
			}
		},
		{
			"__comment": "Element",
			"from": [ 8.65, 24.4498, 1.35 ],
			"to": [ 8.9, 25.1998, 1.6 ],
			"faces": {
				"down": { "uv": [ 8, 6.5, 8.5, 7 ], "texture": "#1_1", "cullface": "down" },
				"up": { "uv": [ 8, 6.5, 8.5, 7 ], "texture": "#1_1", "cullface": "up" },
				"north": { "uv": [ 8, 6.5, 8.5, 7 ], "texture": "#1_1", "cullface": "north" },
				"south": { "uv": [ 8, 6.5, 8.5, 7 ], "texture": "#1_1", "cullface": "south" },
				"west": { "uv": [ 8, 6.5, 8.5, 7 ], "texture": "#1_1", "cullface": "west" },
				"east": { "uv": [ 8, 6.5, 8.5, 7 ], "texture": "#1_1", "cullface": "east" }
			}
		},
		{
			"__comment": "Element",
			"from": [ 7.25, 24.9498, 1.35 ],
			"to": [ 7.5, 25.6998, 1.6 ],
			"faces": {
				"down": { "uv": [ 8.5, 6.5, 8, 7 ], "texture": "#1_1", "cullface": "down" },
				"up": { "uv": [ 8.5, 6.5, 8, 7 ], "texture": "#1_1", "cullface": "up" },
				"north": { "uv": [ 8.5, 6.5, 8, 7 ], "texture": "#1_1", "cullface": "north" },
				"south": { "uv": [ 8.5, 6.5, 8, 7 ], "texture": "#1_1", "cullface": "south" },
				"west": { "uv": [ 8.5, 6.5, 8, 7 ], "texture": "#1_1", "cullface": "west" },
				"east": { "uv": [ 8.5, 6.5, 8, 7 ], "texture": "#1_1", "cullface": "east" }
			}
		},
		{
			"__comment": "Element",
			"from": [ 8.45, 24.9498, 1.35 ],
			"to": [ 8.7, 25.6998, 1.6 ],
			"faces": {
				"down": { "uv": [ 8, 6.5, 8.5, 7 ], "texture": "#1_1", "cullface": "down" },
				"up": { "uv": [ 8, 6.5, 8.5, 7 ], "texture": "#1_1", "cullface": "up" },
				"north": { "uv": [ 8, 6.5, 8.5, 7 ], "texture": "#1_1", "cullface": "north" },
				"south": { "uv": [ 8, 6.5, 8.5, 7 ], "texture": "#1_1", "cullface": "south" },
				"west": { "uv": [ 8, 6.5, 8.5, 7 ], "texture": "#1_1", "cullface": "west" },
				"east": { "uv": [ 8, 6.5, 8.5, 7 ], "texture": "#1_1", "cullface": "east" }
			}
		},
		{
			"__comment": "Element",
			"from": [ 7.45, 25.4498, 1.35 ],
			"to": [ 7.7, 26.1998, 1.6 ],
			"faces": {
				"down": { "uv": [ 8.5, 6.5, 8, 7 ], "texture": "#1_1", "cullface": "down" },
				"up": { "uv": [ 8.5, 6.5, 8, 7 ], "texture": "#1_1", "cullface": "up" },
				"north": { "uv": [ 8.5, 6.5, 8, 7 ], "texture": "#1_1", "cullface": "north" },
				"south": { "uv": [ 8.5, 6.5, 8, 7 ], "texture": "#1_1", "cullface": "south" },
				"west": { "uv": [ 8.5, 6.5, 8, 7 ], "texture": "#1_1", "cullface": "west" },
				"east": { "uv": [ 8.5, 6.5, 8, 7 ], "texture": "#1_1", "cullface": "east" }
			}
		},
		{
			"__comment": "Element",
			"from": [ 8.25, 25.4498, 1.35 ],
			"to": [ 8.5, 26.1998, 1.6 ],
			"faces": {
				"down": { "uv": [ 8, 6.5, 8.5, 7 ], "texture": "#1_1", "cullface": "down" },
				"up": { "uv": [ 8, 6.5, 8.5, 7 ], "texture": "#1_1", "cullface": "up" },
				"north": { "uv": [ 8, 6.5, 8.5, 7 ], "texture": "#1_1", "cullface": "north" },
				"south": { "uv": [ 8, 6.5, 8.5, 7 ], "texture": "#1_1", "cullface": "south" },
				"west": { "uv": [ 8, 6.5, 8.5, 7 ], "texture": "#1_1", "cullface": "west" },
				"east": { "uv": [ 8, 6.5, 8.5, 7 ], "texture": "#1_1", "cullface": "east" }
			}
		},
		{
			"__comment": "Element",
			"from": [ 7.65, 25.9498, 1.35 ],
			"to": [ 7.9, 26.6998, 1.6 ],
			"faces": {
				"down": { "uv": [ 8.5, 6.5, 8, 7 ], "texture": "#1_1", "cullface": "down" },
				"up": { "uv": [ 8.5, 6.5, 8, 7 ], "texture": "#1_1", "cullface": "up" },
				"north": { "uv": [ 8.5, 6.5, 8, 7 ], "texture": "#1_1", "cullface": "north" },
				"south": { "uv": [ 8.5, 6.5, 8, 7 ], "texture": "#1_1", "cullface": "south" },
				"west": { "uv": [ 8.5, 6.5, 8, 7 ], "texture": "#1_1", "cullface": "west" },
				"east": { "uv": [ 8.5, 6.5, 8, 7 ], "texture": "#1_1", "cullface": "east" }
			}
		},
		{
			"__comment": "Element",
			"from": [ 8.05, 25.9498, 1.35 ],
			"to": [ 8.3, 26.6998, 1.6 ],
			"faces": {
				"down": { "uv": [ 8, 6.5, 8.5, 7 ], "texture": "#1_1", "cullface": "down" },
				"up": { "uv": [ 8, 6.5, 8.5, 7 ], "texture": "#1_1", "cullface": "up" },
				"north": { "uv": [ 8, 6.5, 8.5, 7 ], "texture": "#1_1", "cullface": "north" },
				"south": { "uv": [ 8, 6.5, 8.5, 7 ], "texture": "#1_1", "cullface": "south" },
				"west": { "uv": [ 8, 6.5, 8.5, 7 ], "texture": "#1_1", "cullface": "west" },
				"east": { "uv": [ 8, 6.5, 8.5, 7 ], "texture": "#1_1", "cullface": "east" }
			}
		},
		{
			"__comment": "Element",
			"from": [ 6.85, 23.9498, 1.35 ],
			"to": [ 7.1, 24.6998, 1.6 ],
			"faces": {
				"down": { "uv": [ 8.5, 6.5, 8, 7 ], "texture": "#1_1", "cullface": "down" },
				"up": { "uv": [ 8.5, 6.5, 8, 7 ], "texture": "#1_1", "cullface": "up" },
				"north": { "uv": [ 8.5, 6.5, 8, 7 ], "texture": "#1_1", "cullface": "north" },
				"south": { "uv": [ 8.5, 6.5, 8, 7 ], "texture": "#1_1", "cullface": "south" },
				"west": { "uv": [ 8.5, 6.5, 8, 7 ], "texture": "#1_1", "cullface": "west" },
				"east": { "uv": [ 8.5, 6.5, 8, 7 ], "texture": "#1_1", "cullface": "east" }
			}
		},
		{
			"__comment": "Element",
			"from": [ 8.849999, 23.9498, 1.35 ],
			"to": [ 9.099999, 24.6998, 1.6 ],
			"faces": {
				"down": { "uv": [ 8, 6.5, 8.5, 7 ], "texture": "#1_1", "cullface": "down" },
				"up": { "uv": [ 8, 6.5, 8.5, 7 ], "texture": "#1_1", "cullface": "up" },
				"north": { "uv": [ 8, 6.5, 8.5, 7 ], "texture": "#1_1", "cullface": "north" },
				"south": { "uv": [ 8, 6.5, 8.5, 7 ], "texture": "#1_1", "cullface": "south" },
				"west": { "uv": [ 8, 6.5, 8.5, 7 ], "texture": "#1_1", "cullface": "west" },
				"east": { "uv": [ 8, 6.5, 8.5, 7 ], "texture": "#1_1", "cullface": "east" }
			}
		},
		{
			"__comment": "Element",
			"from": [ 7.05, 23.4498, -1.15 ],
			"to": [ 7.3, 24.1998, -0.9 ],
			"faces": {
				"down": { "uv": [ 8.5, 6.5, 8, 7 ], "texture": "#1_1", "cullface": "down" },
				"up": { "uv": [ 8.5, 6.5, 8, 7 ], "texture": "#1_1", "cullface": "up" },
				"north": { "uv": [ 8.5, 6.5, 8, 7 ], "texture": "#1_1", "cullface": "north" },
				"south": { "uv": [ 8.5, 6.5, 8, 7 ], "texture": "#1_1", "cullface": "south" },
				"west": { "uv": [ 8.5, 6.5, 8, 7 ], "texture": "#1_1", "cullface": "west" },
				"east": { "uv": [ 8.5, 6.5, 8, 7 ], "texture": "#1_1", "cullface": "east" }
			}
		},
		{
			"__comment": "Element",
			"from": [ 8.65, 23.4498, -1.15 ],
			"to": [ 8.9, 24.1998, -0.9 ],
			"faces": {
				"down": { "uv": [ 8, 6.5, 8.5, 7 ], "texture": "#1_1", "cullface": "down" },
				"up": { "uv": [ 8, 6.5, 8.5, 7 ], "texture": "#1_1", "cullface": "up" },
				"north": { "uv": [ 8, 6.5, 8.5, 7 ], "texture": "#1_1", "cullface": "north" },
				"south": { "uv": [ 8, 6.5, 8.5, 7 ], "texture": "#1_1", "cullface": "south" },
				"west": { "uv": [ 8, 6.5, 8.5, 7 ], "texture": "#1_1", "cullface": "west" },
				"east": { "uv": [ 8, 6.5, 8.5, 7 ], "texture": "#1_1", "cullface": "east" }
			}
		},
		{
			"__comment": "Element",
			"from": [ 7.25, 23.9498, -1.15 ],
			"to": [ 7.5, 24.6998, -0.9 ],
			"faces": {
				"down": { "uv": [ 8.5, 6.5, 8, 7 ], "texture": "#1_1", "cullface": "down" },
				"up": { "uv": [ 8.5, 6.5, 8, 7 ], "texture": "#1_1", "cullface": "up" },
				"north": { "uv": [ 8.5, 6.5, 8, 7 ], "texture": "#1_1", "cullface": "north" },
				"south": { "uv": [ 8.5, 6.5, 8, 7 ], "texture": "#1_1", "cullface": "south" },
				"west": { "uv": [ 8.5, 6.5, 8, 7 ], "texture": "#1_1", "cullface": "west" },
				"east": { "uv": [ 8.5, 6.5, 8, 7 ], "texture": "#1_1", "cullface": "east" }
			}
		},
		{
			"__comment": "Element",
			"from": [ 8.45, 23.9498, -1.15 ],
			"to": [ 8.7, 24.6998, -0.9 ],
			"faces": {
				"down": { "uv": [ 8, 6.5, 8.5, 7 ], "texture": "#1_1", "cullface": "down" },
				"up": { "uv": [ 8, 6.5, 8.5, 7 ], "texture": "#1_1", "cullface": "up" },
				"north": { "uv": [ 8, 6.5, 8.5, 7 ], "texture": "#1_1", "cullface": "north" },
				"south": { "uv": [ 8, 6.5, 8.5, 7 ], "texture": "#1_1", "cullface": "south" },
				"west": { "uv": [ 8, 6.5, 8.5, 7 ], "texture": "#1_1", "cullface": "west" },
				"east": { "uv": [ 8, 6.5, 8.5, 7 ], "texture": "#1_1", "cullface": "east" }
			}
		},
		{
			"__comment": "Element",
			"from": [ 7.45, 24.4498, -1.15 ],
			"to": [ 7.7, 25.1998, -0.9 ],
			"faces": {
				"down": { "uv": [ 8.5, 6.5, 8, 7 ], "texture": "#1_1", "cullface": "down" },
				"up": { "uv": [ 8.5, 6.5, 8, 7 ], "texture": "#1_1", "cullface": "up" },
				"north": { "uv": [ 8.5, 6.5, 8, 7 ], "texture": "#1_1", "cullface": "north" },
				"south": { "uv": [ 8.5, 6.5, 8, 7 ], "texture": "#1_1", "cullface": "south" },
				"west": { "uv": [ 8.5, 6.5, 8, 7 ], "texture": "#1_1", "cullface": "west" },
				"east": { "uv": [ 8.5, 6.5, 8, 7 ], "texture": "#1_1", "cullface": "east" }
			}
		},
		{
			"__comment": "Element",
			"from": [ 8.25, 24.4498, -1.15 ],
			"to": [ 8.5, 25.1998, -0.9 ],
			"faces": {
				"down": { "uv": [ 8, 6.5, 8.5, 7 ], "texture": "#1_1", "cullface": "down" },
				"up": { "uv": [ 8, 6.5, 8.5, 7 ], "texture": "#1_1", "cullface": "up" },
				"north": { "uv": [ 8, 6.5, 8.5, 7 ], "texture": "#1_1", "cullface": "north" },
				"south": { "uv": [ 8, 6.5, 8.5, 7 ], "texture": "#1_1", "cullface": "south" },
				"west": { "uv": [ 8, 6.5, 8.5, 7 ], "texture": "#1_1", "cullface": "west" },
				"east": { "uv": [ 8, 6.5, 8.5, 7 ], "texture": "#1_1", "cullface": "east" }
			}
		},
		{
			"__comment": "Element",
			"from": [ 7.65, 24.9498, -1.15 ],
			"to": [ 7.9, 25.6998, -0.9 ],
			"faces": {
				"down": { "uv": [ 8.5, 6.5, 8, 7 ], "texture": "#1_1", "cullface": "down" },
				"up": { "uv": [ 8.5, 6.5, 8, 7 ], "texture": "#1_1", "cullface": "up" },
				"north": { "uv": [ 8.5, 6.5, 8, 7 ], "texture": "#1_1", "cullface": "north" },
				"south": { "uv": [ 8.5, 6.5, 8, 7 ], "texture": "#1_1", "cullface": "south" },
				"west": { "uv": [ 8.5, 6.5, 8, 7 ], "texture": "#1_1", "cullface": "west" },
				"east": { "uv": [ 8.5, 6.5, 8, 7 ], "texture": "#1_1", "cullface": "east" }
			}
		},
		{
			"__comment": "Element",
			"from": [ 8.05, 24.9498, -1.15 ],
			"to": [ 8.3, 25.6998, -0.9 ],
			"faces": {
				"down": { "uv": [ 8, 6.5, 8.5, 7 ], "texture": "#1_1", "cullface": "down" },
				"up": { "uv": [ 8, 6.5, 8.5, 7 ], "texture": "#1_1", "cullface": "up" },
				"north": { "uv": [ 8, 6.5, 8.5, 7 ], "texture": "#1_1", "cullface": "north" },
				"south": { "uv": [ 8, 6.5, 8.5, 7 ], "texture": "#1_1", "cullface": "south" },
				"west": { "uv": [ 8, 6.5, 8.5, 7 ], "texture": "#1_1", "cullface": "west" },
				"east": { "uv": [ 8, 6.5, 8.5, 7 ], "texture": "#1_1", "cullface": "east" }
			}
		},
		{
			"__comment": "Element",
			"from": [ 7.85, 25.4498, -1.15 ],
			"to": [ 8.1, 26.1998, -0.9 ],
			"faces": {
				"down": { "uv": [ 8, 6.5, 8.5, 7 ], "texture": "#1_1", "cullface": "down" },
				"up": { "uv": [ 8, 6.5, 8.5, 7 ], "texture": "#1_1", "cullface": "up" },
				"north": { "uv": [ 8, 6.5, 8.5, 7 ], "texture": "#1_1", "cullface": "north" },
				"south": { "uv": [ 8, 6.5, 8.5, 7 ], "texture": "#1_1", "cullface": "south" },
				"west": { "uv": [ 8, 6.5, 8.5, 7 ], "texture": "#1_1", "cullface": "west" },
				"east": { "uv": [ 8, 6.5, 8.5, 7 ], "texture": "#1_1", "cullface": "east" }
			}
		},
		{
			"__comment": "Element",
			"from": [ 7.85, 26.4498, 14.35 ],
			"to": [ 8.1, 27.1998, 14.6 ],
			"faces": {
				"down": { "uv": [ 8, 6.5, 8.5, 7 ], "texture": "#1_1", "cullface": "down" },
				"up": { "uv": [ 8, 6.5, 8.5, 7 ], "texture": "#1_1", "cullface": "up" },
				"north": { "uv": [ 8, 6.5, 8.5, 7 ], "texture": "#1_1", "cullface": "north" },
				"south": { "uv": [ 8, 6.5, 8.5, 7 ], "texture": "#1_1", "cullface": "south" },
				"west": { "uv": [ 8, 6.5, 8.5, 7 ], "texture": "#1_1", "cullface": "west" },
				"east": { "uv": [ 8, 6.5, 8.5, 7 ], "texture": "#1_1", "cullface": "east" }
			}
		},
		{
			"__comment": "Element",
			"from": [ 7.05, 24.4498, 14.35 ],
			"to": [ 7.3, 25.1998, 14.6 ],
			"faces": {
				"down": { "uv": [ 8.5, 6.5, 8, 7 ], "texture": "#1_1", "cullface": "down" },
				"up": { "uv": [ 8.5, 6.5, 8, 7 ], "texture": "#1_1", "cullface": "up" },
				"north": { "uv": [ 8.5, 6.5, 8, 7 ], "texture": "#1_1", "cullface": "north" },
				"south": { "uv": [ 8.5, 6.5, 8, 7 ], "texture": "#1_1", "cullface": "south" },
				"west": { "uv": [ 8.5, 6.5, 8, 7 ], "texture": "#1_1", "cullface": "west" },
				"east": { "uv": [ 8.5, 6.5, 8, 7 ], "texture": "#1_1", "cullface": "east" }
			}
		},
		{
			"__comment": "Element",
			"from": [ 8.65, 24.4498, 14.35 ],
			"to": [ 8.9, 25.1998, 14.6 ],
			"faces": {
				"down": { "uv": [ 8, 6.5, 8.5, 7 ], "texture": "#1_1", "cullface": "down" },
				"up": { "uv": [ 8, 6.5, 8.5, 7 ], "texture": "#1_1", "cullface": "up" },
				"north": { "uv": [ 8, 6.5, 8.5, 7 ], "texture": "#1_1", "cullface": "north" },
				"south": { "uv": [ 8, 6.5, 8.5, 7 ], "texture": "#1_1", "cullface": "south" },
				"west": { "uv": [ 8, 6.5, 8.5, 7 ], "texture": "#1_1", "cullface": "west" },
				"east": { "uv": [ 8, 6.5, 8.5, 7 ], "texture": "#1_1", "cullface": "east" }
			}
		},
		{
			"__comment": "Element",
			"from": [ 7.25, 24.9498, 14.35 ],
			"to": [ 7.5, 25.6998, 14.6 ],
			"faces": {
				"down": { "uv": [ 8.5, 6.5, 8, 7 ], "texture": "#1_1", "cullface": "down" },
				"up": { "uv": [ 8.5, 6.5, 8, 7 ], "texture": "#1_1", "cullface": "up" },
				"north": { "uv": [ 8.5, 6.5, 8, 7 ], "texture": "#1_1", "cullface": "north" },
				"south": { "uv": [ 8.5, 6.5, 8, 7 ], "texture": "#1_1", "cullface": "south" },
				"west": { "uv": [ 8.5, 6.5, 8, 7 ], "texture": "#1_1", "cullface": "west" },
				"east": { "uv": [ 8.5, 6.5, 8, 7 ], "texture": "#1_1", "cullface": "east" }
			}
		},
		{
			"__comment": "Element",
			"from": [ 8.45, 24.9498, 14.35 ],
			"to": [ 8.7, 25.6998, 14.6 ],
			"faces": {
				"down": { "uv": [ 8, 6.5, 8.5, 7 ], "texture": "#1_1", "cullface": "down" },
				"up": { "uv": [ 8, 6.5, 8.5, 7 ], "texture": "#1_1", "cullface": "up" },
				"north": { "uv": [ 8, 6.5, 8.5, 7 ], "texture": "#1_1", "cullface": "north" },
				"south": { "uv": [ 8, 6.5, 8.5, 7 ], "texture": "#1_1", "cullface": "south" },
				"west": { "uv": [ 8, 6.5, 8.5, 7 ], "texture": "#1_1", "cullface": "west" },
				"east": { "uv": [ 8, 6.5, 8.5, 7 ], "texture": "#1_1", "cullface": "east" }
			}
		},
		{
			"__comment": "Element",
			"from": [ 7.45, 25.4498, 14.35 ],
			"to": [ 7.7, 26.1998, 14.6 ],
			"faces": {
				"down": { "uv": [ 8.5, 6.5, 8, 7 ], "texture": "#1_1", "cullface": "down" },
				"up": { "uv": [ 8.5, 6.5, 8, 7 ], "texture": "#1_1", "cullface": "up" },
				"north": { "uv": [ 8.5, 6.5, 8, 7 ], "texture": "#1_1", "cullface": "north" },
				"south": { "uv": [ 8.5, 6.5, 8, 7 ], "texture": "#1_1", "cullface": "south" },
				"west": { "uv": [ 8.5, 6.5, 8, 7 ], "texture": "#1_1", "cullface": "west" },
				"east": { "uv": [ 8.5, 6.5, 8, 7 ], "texture": "#1_1", "cullface": "east" }
			}
		},
		{
			"__comment": "Element",
			"from": [ 8.25, 25.4498, 14.35 ],
			"to": [ 8.5, 26.1998, 14.6 ],
			"faces": {
				"down": { "uv": [ 8, 6.5, 8.5, 7 ], "texture": "#1_1", "cullface": "down" },
				"up": { "uv": [ 8, 6.5, 8.5, 7 ], "texture": "#1_1", "cullface": "up" },
				"north": { "uv": [ 8, 6.5, 8.5, 7 ], "texture": "#1_1", "cullface": "north" },
				"south": { "uv": [ 8, 6.5, 8.5, 7 ], "texture": "#1_1", "cullface": "south" },
				"west": { "uv": [ 8, 6.5, 8.5, 7 ], "texture": "#1_1", "cullface": "west" },
				"east": { "uv": [ 8, 6.5, 8.5, 7 ], "texture": "#1_1", "cullface": "east" }
			}
		},
		{
			"__comment": "Element",
			"from": [ 7.65, 25.9498, 14.35 ],
			"to": [ 7.9, 26.6998, 14.6 ],
			"faces": {
				"down": { "uv": [ 8.5, 6.5, 8, 7 ], "texture": "#1_1", "cullface": "down" },
				"up": { "uv": [ 8.5, 6.5, 8, 7 ], "texture": "#1_1", "cullface": "up" },
				"north": { "uv": [ 8.5, 6.5, 8, 7 ], "texture": "#1_1", "cullface": "north" },
				"south": { "uv": [ 8.5, 6.5, 8, 7 ], "texture": "#1_1", "cullface": "south" },
				"west": { "uv": [ 8.5, 6.5, 8, 7 ], "texture": "#1_1", "cullface": "west" },
				"east": { "uv": [ 8.5, 6.5, 8, 7 ], "texture": "#1_1", "cullface": "east" }
			}
		},
		{
			"__comment": "Element",
			"from": [ 8.05, 25.9498, 14.35 ],
			"to": [ 8.3, 26.6998, 14.6 ],
			"faces": {
				"down": { "uv": [ 8, 6.5, 8.5, 7 ], "texture": "#1_1", "cullface": "down" },
				"up": { "uv": [ 8, 6.5, 8.5, 7 ], "texture": "#1_1", "cullface": "up" },
				"north": { "uv": [ 8, 6.5, 8.5, 7 ], "texture": "#1_1", "cullface": "north" },
				"south": { "uv": [ 8, 6.5, 8.5, 7 ], "texture": "#1_1", "cullface": "south" },
				"west": { "uv": [ 8, 6.5, 8.5, 7 ], "texture": "#1_1", "cullface": "west" },
				"east": { "uv": [ 8, 6.5, 8.5, 7 ], "texture": "#1_1", "cullface": "east" }
			}
		},
		{
			"__comment": "Element",
			"from": [ 6.85, 23.9498, 14.35 ],
			"to": [ 7.1, 24.6998, 14.6 ],
			"faces": {
				"down": { "uv": [ 8.5, 6.5, 8, 7 ], "texture": "#1_1", "cullface": "down" },
				"up": { "uv": [ 8.5, 6.5, 8, 7 ], "texture": "#1_1", "cullface": "up" },
				"north": { "uv": [ 8.5, 6.5, 8, 7 ], "texture": "#1_1", "cullface": "north" },
				"south": { "uv": [ 8.5, 6.5, 8, 7 ], "texture": "#1_1", "cullface": "south" },
				"west": { "uv": [ 8.5, 6.5, 8, 7 ], "texture": "#1_1", "cullface": "west" },
				"east": { "uv": [ 8.5, 6.5, 8, 7 ], "texture": "#1_1", "cullface": "east" }
			}
		},
		{
			"__comment": "Element",
			"from": [ 8.849999, 23.9498, 14.35 ],
			"to": [ 9.099999, 24.6998, 14.6 ],
			"faces": {
				"down": { "uv": [ 8, 6.5, 8.5, 7 ], "texture": "#1_1", "cullface": "down" },
				"up": { "uv": [ 8, 6.5, 8.5, 7 ], "texture": "#1_1", "cullface": "up" },
				"north": { "uv": [ 8, 6.5, 8.5, 7 ], "texture": "#1_1", "cullface": "north" },
				"south": { "uv": [ 8, 6.5, 8.5, 7 ], "texture": "#1_1", "cullface": "south" },
				"west": { "uv": [ 8, 6.5, 8.5, 7 ], "texture": "#1_1", "cullface": "west" },
				"east": { "uv": [ 8, 6.5, 8.5, 7 ], "texture": "#1_1", "cullface": "east" }
			}
		},
		{
			"__comment": "Element",
			"from": [ 7.05, 23.4498, 16.85 ],
			"to": [ 7.3, 24.1998, 17.1 ],
			"faces": {
				"down": { "uv": [ 8.5, 6.5, 8, 7 ], "texture": "#1_1", "cullface": "down" },
				"up": { "uv": [ 8.5, 6.5, 8, 7 ], "texture": "#1_1", "cullface": "up" },
				"north": { "uv": [ 8.5, 6.5, 8, 7 ], "texture": "#1_1", "cullface": "north" },
				"south": { "uv": [ 8.5, 6.5, 8, 7 ], "texture": "#1_1", "cullface": "south" },
				"west": { "uv": [ 8.5, 6.5, 8, 7 ], "texture": "#1_1", "cullface": "west" },
				"east": { "uv": [ 8.5, 6.5, 8, 7 ], "texture": "#1_1", "cullface": "east" }
			}
		},
		{
			"__comment": "Element",
			"from": [ 8.65, 23.4498, 16.85 ],
			"to": [ 8.9, 24.1998, 17.1 ],
			"faces": {
				"down": { "uv": [ 8, 6.5, 8.5, 7 ], "texture": "#1_1", "cullface": "down" },
				"up": { "uv": [ 8, 6.5, 8.5, 7 ], "texture": "#1_1", "cullface": "up" },
				"north": { "uv": [ 8, 6.5, 8.5, 7 ], "texture": "#1_1", "cullface": "north" },
				"south": { "uv": [ 8, 6.5, 8.5, 7 ], "texture": "#1_1", "cullface": "south" },
				"west": { "uv": [ 8, 6.5, 8.5, 7 ], "texture": "#1_1", "cullface": "west" },
				"east": { "uv": [ 8, 6.5, 8.5, 7 ], "texture": "#1_1", "cullface": "east" }
			}
		},
		{
			"__comment": "Element",
			"from": [ 7.25, 23.9498, 16.85 ],
			"to": [ 7.5, 24.6998, 17.1 ],
			"faces": {
				"down": { "uv": [ 8.5, 6.5, 8, 7 ], "texture": "#1_1", "cullface": "down" },
				"up": { "uv": [ 8.5, 6.5, 8, 7 ], "texture": "#1_1", "cullface": "up" },
				"north": { "uv": [ 8.5, 6.5, 8, 7 ], "texture": "#1_1", "cullface": "north" },
				"south": { "uv": [ 8.5, 6.5, 8, 7 ], "texture": "#1_1", "cullface": "south" },
				"west": { "uv": [ 8.5, 6.5, 8, 7 ], "texture": "#1_1", "cullface": "west" },
				"east": { "uv": [ 8.5, 6.5, 8, 7 ], "texture": "#1_1", "cullface": "east" }
			}
		},
		{
			"__comment": "Element",
			"from": [ 8.45, 23.9498, 16.85 ],
			"to": [ 8.7, 24.6998, 17.1 ],
			"faces": {
				"down": { "uv": [ 8, 6.5, 8.5, 7 ], "texture": "#1_1", "cullface": "down" },
				"up": { "uv": [ 8, 6.5, 8.5, 7 ], "texture": "#1_1", "cullface": "up" },
				"north": { "uv": [ 8, 6.5, 8.5, 7 ], "texture": "#1_1", "cullface": "north" },
				"south": { "uv": [ 8, 6.5, 8.5, 7 ], "texture": "#1_1", "cullface": "south" },
				"west": { "uv": [ 8, 6.5, 8.5, 7 ], "texture": "#1_1", "cullface": "west" },
				"east": { "uv": [ 8, 6.5, 8.5, 7 ], "texture": "#1_1", "cullface": "east" }
			}
		},
		{
			"__comment": "Element",
			"from": [ 7.45, 24.4498, 16.85 ],
			"to": [ 7.7, 25.1998, 17.1 ],
			"faces": {
				"down": { "uv": [ 8.5, 6.5, 8, 7 ], "texture": "#1_1", "cullface": "down" },
				"up": { "uv": [ 8.5, 6.5, 8, 7 ], "texture": "#1_1", "cullface": "up" },
				"north": { "uv": [ 8.5, 6.5, 8, 7 ], "texture": "#1_1", "cullface": "north" },
				"south": { "uv": [ 8.5, 6.5, 8, 7 ], "texture": "#1_1", "cullface": "south" },
				"west": { "uv": [ 8.5, 6.5, 8, 7 ], "texture": "#1_1", "cullface": "west" },
				"east": { "uv": [ 8.5, 6.5, 8, 7 ], "texture": "#1_1", "cullface": "east" }
			}
		},
		{
			"__comment": "Element",
			"from": [ 8.25, 24.4498, 16.85 ],
			"to": [ 8.5, 25.1998, 17.1 ],
			"faces": {
				"down": { "uv": [ 8, 6.5, 8.5, 7 ], "texture": "#1_1", "cullface": "down" },
				"up": { "uv": [ 8, 6.5, 8.5, 7 ], "texture": "#1_1", "cullface": "up" },
				"north": { "uv": [ 8, 6.5, 8.5, 7 ], "texture": "#1_1", "cullface": "north" },
				"south": { "uv": [ 8, 6.5, 8.5, 7 ], "texture": "#1_1", "cullface": "south" },
				"west": { "uv": [ 8, 6.5, 8.5, 7 ], "texture": "#1_1", "cullface": "west" },
				"east": { "uv": [ 8, 6.5, 8.5, 7 ], "texture": "#1_1", "cullface": "east" }
			}
		},
		{
			"__comment": "Element",
			"from": [ 7.65, 24.9498, 16.85 ],
			"to": [ 7.9, 25.6998, 17.1 ],
			"faces": {
				"down": { "uv": [ 8.5, 6.5, 8, 7 ], "texture": "#1_1", "cullface": "down" },
				"up": { "uv": [ 8.5, 6.5, 8, 7 ], "texture": "#1_1", "cullface": "up" },
				"north": { "uv": [ 8.5, 6.5, 8, 7 ], "texture": "#1_1", "cullface": "north" },
				"south": { "uv": [ 8.5, 6.5, 8, 7 ], "texture": "#1_1", "cullface": "south" },
				"west": { "uv": [ 8.5, 6.5, 8, 7 ], "texture": "#1_1", "cullface": "west" },
				"east": { "uv": [ 8.5, 6.5, 8, 7 ], "texture": "#1_1", "cullface": "east" }
			}
		},
		{
			"__comment": "Element",
			"from": [ 8.05, 24.9498, 16.85 ],
			"to": [ 8.3, 25.6998, 17.1 ],
			"faces": {
				"down": { "uv": [ 8, 6.5, 8.5, 7 ], "texture": "#1_1", "cullface": "down" },
				"up": { "uv": [ 8, 6.5, 8.5, 7 ], "texture": "#1_1", "cullface": "up" },
				"north": { "uv": [ 8, 6.5, 8.5, 7 ], "texture": "#1_1", "cullface": "north" },
				"south": { "uv": [ 8, 6.5, 8.5, 7 ], "texture": "#1_1", "cullface": "south" },
				"west": { "uv": [ 8, 6.5, 8.5, 7 ], "texture": "#1_1", "cullface": "west" },
				"east": { "uv": [ 8, 6.5, 8.5, 7 ], "texture": "#1_1", "cullface": "east" }
			}
		},
		{
			"__comment": "Element",
			"from": [ 7.85, 25.4498, 16.85 ],
			"to": [ 8.1, 26.1998, 17.1 ],
			"faces": {
				"down": { "uv": [ 8, 6.5, 8.5, 7 ], "texture": "#1_1", "cullface": "down" },
				"up": { "uv": [ 8, 6.5, 8.5, 7 ], "texture": "#1_1", "cullface": "up" },
				"north": { "uv": [ 8, 6.5, 8.5, 7 ], "texture": "#1_1", "cullface": "north" },
				"south": { "uv": [ 8, 6.5, 8.5, 7 ], "texture": "#1_1", "cullface": "south" },
				"west": { "uv": [ 8, 6.5, 8.5, 7 ], "texture": "#1_1", "cullface": "west" },
				"east": { "uv": [ 8, 6.5, 8.5, 7 ], "texture": "#1_1", "cullface": "east" }
			}
		}
	],
	"display": {
		"thirdperson_righthand": {
			"rotation":  [ 67.5, 0, 0 ],
			"translation":  [ -5.75, 7.25, -9.25 ]
		},
		"gui": {
			"rotation":  [ 12, 106, 0 ],
			"translation":  [ 0.25, -2.5, 0 ],
			"scale":  [ 0.4, 0.4, 0.4 ]
		},
		"head": {
			"rotation":  [ 0, 90, 0 ],
			"translation":  [ -13.25, -26.5, 0 ],
			"scale":  [ 1.5, 1.5, 1.5 ]
		},
		"fixed": {
			"rotation":  [ 0, -90, 0 ],
			"translation":  [ 0, 4.5, -7.25 ],
			"scale":  [ 1.8457, 1.8457, 1.8457 ]
		}
	}
}