{
	"__comment": "Designed by Ichristoffee with Cubik Studio - https://cubik.studio",
	"textures": {
		"2": "custom/colors/white",
		"3": "custom/colors/blue_light",
		"particle": "custom/colors/bone"
	},
	"elements": [ 	 
		{
			"__comment": "Element",
			"from": [ -5.6702, 10.6639, 3.0878 ],
			"to": [ 3.2002, 14.13016, 11.73644 ],
			"faces": {
				"down": { "uv": [ 10, 6.7, 11, 6 ], "texture": "#3", "rotation": 180 },
				"up": { "uv": [ 10, 6.7, 11, 6 ], "texture": "#3", "rotation": 180 },
				"north": { "uv": [ 10, 6.7, 11, 6 ], "texture": "#3", "rotation": 180 },
				"south": { "uv": [ 10, 6.7, 11, 6 ], "texture": "#3", "rotation": 180 },
				"west": { "uv": [ 10, 6.7, 11, 6 ], "texture": "#3", "rotation": 180 },
				"east": { "uv": [ 10, 6.7, 11, 6 ], "texture": "#3", "rotation": 180 }
			}
		},
		{
			"__comment": "Element",
			"from": [ 4.721, 21.785, 0.4021 ],
			"to": [ 17.38712, 28.00845, 15.43165 ],
			"rotation": { "origin": [ 11.04702, 20.60334, 7.987539 ], "axis": "z", "angle": 22.5 },
			"faces": {
				"down": { "uv": [ 10, 6.7, 11, 6 ], "texture": "#3", "rotation": 180 },
				"up": { "uv": [ 10, 6.7, 11, 6 ], "texture": "#3", "rotation": 180 },
				"north": { "uv": [ 10, 6.7, 11, 6 ], "texture": "#3", "rotation": 180 },
				"south": { "uv": [ 10, 6.7, 11, 6 ], "texture": "#3", "rotation": 180 },
				"west": { "uv": [ 10, 6.7, 11, 6 ], "texture": "#3", "rotation": 180 },
				"east": { "uv": [ 10, 6.7, 11, 6 ], "texture": "#3", "rotation": 180 }
			}
		},
		{
			"__comment": "Element",
			"from": [ 13.7758, 6.0733, 0.1959 ],
			"to": [ 20.65036, 8.75965, 6.89859 ],
			"faces": {
				"down": { "uv": [ 10, 6.7, 11, 6 ], "texture": "#3" },
				"up": { "uv": [ 10, 6.7, 11, 6 ], "texture": "#3" },
				"north": { "uv": [ 10, 6.7, 11, 6 ], "texture": "#3", "rotation": 180 },
				"south": { "uv": [ 10, 6.7, 11, 6 ], "texture": "#3", "rotation": 180 },
				"west": { "uv": [ 10, 6.7, 11, 6 ], "texture": "#3", "rotation": 180 },
				"east": { "uv": [ 10, 6.7, 11, 6 ], "texture": "#3", "rotation": 180 }
			}
		},
		{
			"__comment": "Element",
			"from": [ 13.1714, 3.9596, 14.2642 ],
			"to": [ 17.57111, 5.67886, 18.55392 ],
			"rotation": { "origin": [ 15.37128, 5.54826, 16.41851 ], "axis": "z", "angle": -22.5 },
			"faces": {
				"down": { "uv": [ 10, 6.7, 11, 6 ], "texture": "#3" },
				"up": { "uv": [ 10, 6.7, 11, 6 ], "texture": "#3" },
				"north": { "uv": [ 10, 6.7, 11, 6 ], "texture": "#3", "rotation": 180 },
				"south": { "uv": [ 10, 6.7, 11, 6 ], "texture": "#3", "rotation": 180 },
				"west": { "uv": [ 10, 6.7, 11, 6 ], "texture": "#3", "rotation": 180 },
				"east": { "uv": [ 10, 6.7, 11, 6 ], "texture": "#3", "rotation": 180 }
			}
		},
		{
			"__comment": "Element",
			"from": [ -4.9311, 13.1469, 3.827 ],
			"to": [ 2.4609, 16.4859, 10.883 ],
			"faces": {
				"down": { "uv": [ 8, 4.5, 9, 5.2 ], "texture": "#3", "rotation": 180 },
				"up": { "uv": [ 8, 4.5, 9, 5.2 ], "texture": "#3", "rotation": 180 },
				"north": { "uv": [ 3.5, 10.2, 4.5, 9.5 ], "texture": "#3", "rotation": 180 },
				"south": { "uv": [ 3.5, 10.2, 4.5, 9.5 ], "texture": "#3", "rotation": 180 },
				"west": { "uv": [ 3.5, 10.2, 4.5, 9.5 ], "texture": "#3", "rotation": 180 },
				"east": { "uv": [ 3.5, 10.2, 4.5, 9.5 ], "texture": "#3", "rotation": 180 }
			}
		},
		{
			"__comment": "Element",
			"from": [ 5.6449, 24.8888, 1.3261 ],
			"to": [ 16.46302, 30.95318, 14.36486 ],
			"rotation": { "origin": [ 11.04702, 20.60334, 7.987539 ], "axis": "z", "angle": 22.5 },
			"faces": {
				"down": { "uv": [ 8, 4.5, 9, 5.2 ], "texture": "#3", "rotation": 180 },
				"up": { "uv": [ 8, 4.5, 9, 5.2 ], "texture": "#3", "rotation": 180 },
				"north": { "uv": [ 3.5, 10.2, 4.5, 9.5 ], "texture": "#3", "rotation": 180 },
				"south": { "uv": [ 3.5, 10.2, 4.5, 9.5 ], "texture": "#3", "rotation": 180 },
				"west": { "uv": [ 3.5, 10.2, 4.5, 9.5 ], "texture": "#3", "rotation": 180 },
				"east": { "uv": [ 3.5, 10.2, 4.5, 9.5 ], "texture": "#3", "rotation": 180 }
			}
		},
		{
			"__comment": "Element",
			"from": [ 14.3488, 7.9977, 0.8573 ],
			"to": [ 20.0776, 10.58542, 6.3257 ],
			"faces": {
				"down": { "uv": [ 8, 4.5, 9, 5.2 ], "texture": "#3" },
				"up": { "uv": [ 8, 4.5, 9, 5.2 ], "texture": "#3" },
				"north": { "uv": [ 3.5, 10.2, 4.5, 9.5 ], "texture": "#3", "rotation": 180 },
				"south": { "uv": [ 3.5, 10.2, 4.5, 9.5 ], "texture": "#3", "rotation": 180 },
				"west": { "uv": [ 3.5, 10.2, 4.5, 9.5 ], "texture": "#3", "rotation": 180 },
				"east": { "uv": [ 3.5, 10.2, 4.5, 9.5 ], "texture": "#3", "rotation": 180 }
			}
		},
		{
			"__comment": "Element",
			"from": [ 13.5381, 5.1912, 14.6875 ],
			"to": [ 17.20453, 6.84735, 18.18727 ],
			"rotation": { "origin": [ 15.37128, 5.54826, 16.41851 ], "axis": "z", "angle": -22.5 },
			"faces": {
				"down": { "uv": [ 8, 4.5, 9, 5.2 ], "texture": "#3" },
				"up": { "uv": [ 8, 4.5, 9, 5.2 ], "texture": "#3" },
				"north": { "uv": [ 3.5, 10.2, 4.5, 9.5 ], "texture": "#3", "rotation": 180 },
				"south": { "uv": [ 3.5, 10.2, 4.5, 9.5 ], "texture": "#3", "rotation": 180 },
				"west": { "uv": [ 3.5, 10.2, 4.5, 9.5 ], "texture": "#3", "rotation": 180 },
				"east": { "uv": [ 3.5, 10.2, 4.5, 9.5 ], "texture": "#3", "rotation": 180 }
			}
		},
		{
			"__comment": "Element",
			"from": [ -3.4527, 11.3661, 5.3054 ],
			"to": [ 0.9825003, 17.40822, 9.51884 ],
			"faces": {
				"down": { "uv": [ 8, 4.5, 9, 5.2 ], "texture": "#2", "rotation": 180 },
				"up": { "uv": [ 8, 4.5, 9, 5.2 ], "texture": "#2", "rotation": 180 },
				"north": { "uv": [ 8, 4.5, 9, 5.2 ], "texture": "#2", "rotation": 180 },
				"south": { "uv": [ 8, 4.5, 9, 5.2 ], "texture": "#2", "rotation": 180 },
				"west": { "uv": [ 8, 4.5, 9, 5.2 ], "texture": "#2", "rotation": 180 },
				"east": { "uv": [ 8, 4.5, 9, 5.2 ], "texture": "#2", "rotation": 180 }
			}
		},
		{
			"__comment": "Element",
			"from": [ 7.4929, 22.6628, 3.1741 ],
			"to": [ 14.61502, 32.10608, 12.65965 ],
			"rotation": { "origin": [ 11.04702, 20.60334, 7.987539 ], "axis": "z", "angle": 22.5 },
			"faces": {
				"down": { "uv": [ 8, 4.5, 9, 5.2 ], "texture": "#2", "rotation": 180 },
				"up": { "uv": [ 8, 4.5, 9, 5.2 ], "texture": "#2", "rotation": 180 },
				"north": { "uv": [ 8, 4.5, 9, 5.2 ], "texture": "#2", "rotation": 180 },
				"south": { "uv": [ 8, 4.5, 9, 5.2 ], "texture": "#2", "rotation": 180 },
				"west": { "uv": [ 8, 4.5, 9, 5.2 ], "texture": "#2", "rotation": 180 },
				"east": { "uv": [ 8, 4.5, 9, 5.2 ], "texture": "#2", "rotation": 180 }
			}
		},
		{
			"__comment": "Element",
			"from": [ 15.4946, 6.6175, 1.9145 ],
			"to": [ 18.93188, 11.30014, 5.17991 ],
			"faces": {
				"down": { "uv": [ 8, 4.5, 9, 5.2 ], "texture": "#2" },
				"up": { "uv": [ 8, 4.5, 9, 5.2 ], "texture": "#2" },
				"north": { "uv": [ 8, 4.5, 9, 5.2 ], "texture": "#2", "rotation": 180 },
				"south": { "uv": [ 8, 4.5, 9, 5.2 ], "texture": "#2", "rotation": 180 },
				"west": { "uv": [ 8, 4.5, 9, 5.2 ], "texture": "#2", "rotation": 180 },
				"east": { "uv": [ 8, 4.5, 9, 5.2 ], "texture": "#2", "rotation": 180 }
			}
		},
		{
			"__comment": "Element",
			"from": [ 14.2714, 4.3079, 15.3641 ],
			"to": [ 16.47126, 7.75791, 17.45397 ],
			"rotation": { "origin": [ 15.37128, 5.54826, 16.41851 ], "axis": "z", "angle": -22.5 },
			"faces": {
				"down": { "uv": [ 8, 4.5, 9, 5.2 ], "texture": "#2" },
				"up": { "uv": [ 8, 4.5, 9, 5.2 ], "texture": "#2" },
				"north": { "uv": [ 8, 4.5, 9, 5.2 ], "texture": "#2", "rotation": 180 },
				"south": { "uv": [ 8, 4.5, 9, 5.2 ], "texture": "#2", "rotation": 180 },
				"west": { "uv": [ 8, 4.5, 9, 5.2 ], "texture": "#2", "rotation": 180 },
				"east": { "uv": [ 8, 4.5, 9, 5.2 ], "texture": "#2", "rotation": 180 }
			}
		},
		{
			"__comment": "Element",
			"from": [ -3.3342, 0.0708, 4.5225 ],
			"to": [ 1.7058, 1.3308, 9.9825 ],
			"faces": {
				"down": { "uv": [ 10, 6.7, 11, 6 ], "texture": "#particle", "rotation": 180 },
				"up": { "uv": [ 10, 6.7, 11, 6 ], "texture": "#particle", "rotation": 180 },
				"north": { "uv": [ 10, 6.7, 11, 6 ], "texture": "#particle", "rotation": 180 },
				"south": { "uv": [ 10, 6.7, 11, 6 ], "texture": "#particle", "rotation": 180 },
				"west": { "uv": [ 10, 6.7, 11, 6 ], "texture": "#particle", "rotation": 180 },
				"east": { "uv": [ 10, 6.7, 11, 6 ], "texture": "#particle", "rotation": 180 }
			}
		},
		{
			"__comment": "Element",
			"from": [ 5.6345, 0.0708, 3.7725 ],
			"to": [ 11.72137, 1.3308, 10.87312 ],
			"faces": {
				"down": { "uv": [ 10, 6.7, 11, 6 ], "texture": "#particle", "rotation": 180 },
				"up": { "uv": [ 10, 6.7, 11, 6 ], "texture": "#particle", "rotation": 180 },
				"north": { "uv": [ 10, 6.7, 11, 6 ], "texture": "#particle", "rotation": 180 },
				"south": { "uv": [ 10, 6.7, 11, 6 ], "texture": "#particle", "rotation": 180 },
				"west": { "uv": [ 10, 6.7, 11, 6 ], "texture": "#particle", "rotation": 180 },
				"east": { "uv": [ 10, 6.7, 11, 6 ], "texture": "#particle", "rotation": 180 }
			}
		},
		{
			"__comment": "Element",
			"from": [ 15.3899, 0.1271, 1.9565 ],
			"to": [ 18.5147, 0.9083, 5.3417 ],
			"faces": {
				"down": { "uv": [ 10, 6.7, 11, 6 ], "texture": "#particle" },
				"up": { "uv": [ 10, 6.7, 11, 6 ], "texture": "#particle" },
				"north": { "uv": [ 10, 6.7, 11, 6 ], "texture": "#particle", "rotation": 180 },
				"south": { "uv": [ 10, 6.7, 11, 6 ], "texture": "#particle", "rotation": 180 },
				"west": { "uv": [ 10, 6.7, 11, 6 ], "texture": "#particle", "rotation": 180 },
				"east": { "uv": [ 10, 6.7, 11, 6 ], "texture": "#particle", "rotation": 180 }
			}
		},
		{
			"__comment": "Element",
			"from": [ 14.0325, 0.074, 15.391 ],
			"to": [ 16.03237, 0.57397, 17.55753 ],
			"faces": {
				"down": { "uv": [ 10, 6.7, 11, 6 ], "texture": "#particle" },
				"up": { "uv": [ 10, 6.7, 11, 6 ], "texture": "#particle" },
				"north": { "uv": [ 10, 6.7, 11, 6 ], "texture": "#particle", "rotation": 180 },
				"south": { "uv": [ 10, 6.7, 11, 6 ], "texture": "#particle", "rotation": 180 },
				"west": { "uv": [ 10, 6.7, 11, 6 ], "texture": "#particle", "rotation": 180 },
				"east": { "uv": [ 10, 6.7, 11, 6 ], "texture": "#particle", "rotation": 180 }
			}
		},
		{
			"__comment": "Element",
			"from": [ -2.9142, 1.3308, 5.4675 ],
			"to": [ 0.4458003, 5.1108, 8.8275 ],
			"rotation": { "origin": [ -2.91423, 1.33084, 5.46754 ], "axis": "z", "angle": -22.5 },
			"faces": {
				"down": { "uv": [ 10, 6.7, 11, 6 ], "texture": "#particle", "rotation": 180 },
				"up": { "uv": [ 10, 6.7, 11, 6 ], "texture": "#particle", "rotation": 180 },
				"north": { "uv": [ 10, 6.7, 11, 6 ], "texture": "#particle", "rotation": 180 },
				"south": { "uv": [ 10, 6.7, 11, 6 ], "texture": "#particle", "rotation": 180 },
				"west": { "uv": [ 10, 6.7, 11, 6 ], "texture": "#particle", "rotation": 180 },
				"east": { "uv": [ 10, 6.7, 11, 6 ], "texture": "#particle", "rotation": 180 }
			}
		},
		{
			"__comment": "Element",
			"from": [ 6.0545, 1.5808, 4.7175 ],
			"to": [ 10.46137, 9.39205, 9.71812 ],
			"rotation": { "origin": [ 6.585771, 1.58084, 5.46754 ], "axis": "z", "angle": -22.5 },
			"faces": {
				"down": { "uv": [ 10, 6.7, 11, 6 ], "texture": "#particle", "rotation": 180 },
				"up": { "uv": [ 10, 6.7, 11, 6 ], "texture": "#particle", "rotation": 180 },
				"north": { "uv": [ 10, 6.7, 11, 6 ], "texture": "#particle", "rotation": 180 },
				"south": { "uv": [ 10, 6.7, 11, 6 ], "texture": "#particle", "rotation": 180 },
				"west": { "uv": [ 10, 6.7, 11, 6 ], "texture": "#particle", "rotation": 180 },
				"east": { "uv": [ 10, 6.7, 11, 6 ], "texture": "#particle", "rotation": 180 }
			}
		},
		{
			"__comment": "Element",
			"from": [ 14.5509, 0.7148, 2.6726 ],
			"to": [ 16.6341, 3.0584, 4.7558 ],
			"rotation": { "origin": [ 16.95791, 4.88413, 3.64085 ], "axis": "z", "angle": 22.5 },
			"faces": {
				"down": { "uv": [ 10, 6.7, 11, 6 ], "texture": "#particle" },
				"up": { "uv": [ 10, 6.7, 11, 6 ], "texture": "#particle" },
				"north": { "uv": [ 10, 6.7, 11, 6 ], "texture": "#particle", "rotation": 180 },
				"south": { "uv": [ 10, 6.7, 11, 6 ], "texture": "#particle", "rotation": 180 },
				"west": { "uv": [ 10, 6.7, 11, 6 ], "texture": "#particle", "rotation": 180 },
				"east": { "uv": [ 10, 6.7, 11, 6 ], "texture": "#particle", "rotation": 180 }
			}
		},
		{
			"__comment": "Element",
			"from": [ 13.4955, 0.5751, 15.8493 ],
			"to": [ 14.82875, 2.075, 17.18255 ],
			"rotation": { "origin": [ 15.03604, 3.24351, 16.46898 ], "axis": "z", "angle": 22.5 },
			"faces": {
				"down": { "uv": [ 10, 6.7, 11, 6 ], "texture": "#particle" },
				"up": { "uv": [ 10, 6.7, 11, 6 ], "texture": "#particle" },
				"north": { "uv": [ 10, 6.7, 11, 6 ], "texture": "#particle", "rotation": 180 },
				"south": { "uv": [ 10, 6.7, 11, 6 ], "texture": "#particle", "rotation": 180 },
				"west": { "uv": [ 10, 6.7, 11, 6 ], "texture": "#particle", "rotation": 180 },
				"east": { "uv": [ 10, 6.7, 11, 6 ], "texture": "#particle", "rotation": 180 }
			}
		},
		{
			"__comment": "Element",
			"from": [ -1.7592, 3.4308, 5.4675 ],
			"to": [ 1.6008, 8.8908, 8.8275 ],
			"faces": {
				"down": { "uv": [ 10, 6.7, 11, 6 ], "texture": "#particle", "rotation": 180 },
				"up": { "uv": [ 10, 6.7, 11, 6 ], "texture": "#particle", "rotation": 180 },
				"north": { "uv": [ 10, 6.7, 11, 6 ], "texture": "#particle", "rotation": 180 },
				"south": { "uv": [ 10, 6.7, 11, 6 ], "texture": "#particle", "rotation": 180 },
				"west": { "uv": [ 10, 6.7, 11, 6 ], "texture": "#particle", "rotation": 180 },
				"east": { "uv": [ 10, 6.7, 11, 6 ], "texture": "#particle", "rotation": 180 }
			}
		},
		{
			"__comment": "Element",
			"from": [ 8.709499, 7.1652, 4.7175 ],
			"to": [ 13.11637, 21.78145, 9.71812 ],
			"faces": {
				"down": { "uv": [ 10, 6.7, 11, 6 ], "texture": "#particle", "rotation": 180 },
				"up": { "uv": [ 10, 6.7, 11, 6 ], "texture": "#particle", "rotation": 180 },
				"north": { "uv": [ 10, 6.7, 11, 6 ], "texture": "#particle", "rotation": 180 },
				"south": { "uv": [ 10, 6.7, 11, 6 ], "texture": "#particle", "rotation": 180 },
				"west": { "uv": [ 10, 6.7, 11, 6 ], "texture": "#particle", "rotation": 180 },
				"east": { "uv": [ 10, 6.7, 11, 6 ], "texture": "#particle", "rotation": 180 }
			}
		},
		{
			"__comment": "Element",
			"from": [ 15.455, 2.0853, 2.6726 ],
			"to": [ 17.5382, 5.4705, 4.7558 ],
			"faces": {
				"down": { "uv": [ 10, 6.7, 11, 6 ], "texture": "#particle" },
				"up": { "uv": [ 10, 6.7, 11, 6 ], "texture": "#particle" },
				"north": { "uv": [ 10, 6.7, 11, 6 ], "texture": "#particle", "rotation": 180 },
				"south": { "uv": [ 10, 6.7, 11, 6 ], "texture": "#particle", "rotation": 180 },
				"west": { "uv": [ 10, 6.7, 11, 6 ], "texture": "#particle", "rotation": 180 },
				"east": { "uv": [ 10, 6.7, 11, 6 ], "texture": "#particle", "rotation": 180 }
			}
		},
		{
			"__comment": "Element",
			"from": [ 14.0742, 1.4072, 15.8493 ],
			"to": [ 15.40745, 3.57373, 17.18255 ],
			"faces": {
				"down": { "uv": [ 10, 6.7, 11, 6 ], "texture": "#particle" },
				"up": { "uv": [ 10, 6.7, 11, 6 ], "texture": "#particle" },
				"north": { "uv": [ 10, 6.7, 11, 6 ], "texture": "#particle", "rotation": 180 },
				"south": { "uv": [ 10, 6.7, 11, 6 ], "texture": "#particle", "rotation": 180 },
				"west": { "uv": [ 10, 6.7, 11, 6 ], "texture": "#particle", "rotation": 180 },
				"east": { "uv": [ 10, 6.7, 11, 6 ], "texture": "#particle", "rotation": 180 }
			}
		},
		{
			"__comment": "Element",
			"from": [ -1.4442, 7.5258, 5.4675 ],
			"to": [ 1.9158, 10.8858, 8.8275 ],
			"rotation": { "origin": [ -1.444229, 7.52584, 5.46754 ], "axis": "z", "angle": 22.5 },
			"faces": {
				"down": { "uv": [ 10, 6.7, 11, 6 ], "texture": "#particle", "rotation": 180 },
				"up": { "uv": [ 10, 6.7, 11, 6 ], "texture": "#particle", "rotation": 180 },
				"north": { "uv": [ 10, 6.7, 11, 6 ], "texture": "#particle", "rotation": 180 },
				"south": { "uv": [ 10, 6.7, 11, 6 ], "texture": "#particle", "rotation": 180 },
				"west": { "uv": [ 10, 6.7, 11, 6 ], "texture": "#particle", "rotation": 180 },
				"east": { "uv": [ 10, 6.7, 11, 6 ], "texture": "#particle", "rotation": 180 }
			}
		},
		{
			"__comment": "Element",
			"from": [ 9.0245, 20.3071, 4.7175 ],
			"to": [ 13.43137, 25.62022, 9.71812 ],
			"rotation": { "origin": [ 9.555771, 20.41646, 5.46754 ], "axis": "z", "angle": 22.5 },
			"faces": {
				"down": { "uv": [ 10, 6.7, 11, 6 ], "texture": "#particle", "rotation": 180 },
				"up": { "uv": [ 10, 6.7, 11, 6 ], "texture": "#particle", "rotation": 180 },
				"north": { "uv": [ 10, 6.7, 11, 6 ], "texture": "#particle", "rotation": 180 },
				"south": { "uv": [ 10, 6.7, 11, 6 ], "texture": "#particle", "rotation": 180 },
				"west": { "uv": [ 10, 6.7, 11, 6 ], "texture": "#particle", "rotation": 180 },
				"east": { "uv": [ 10, 6.7, 11, 6 ], "texture": "#particle", "rotation": 180 }
			}
		},
		{
			"__comment": "Element",
			"from": [ 15.282, 4.7818, 2.6726 ],
			"to": [ 17.3652, 6.865, 4.7558 ],
			"rotation": { "origin": [ 16.95791, 4.75913, 3.64085 ], "axis": "z", "angle": -22.5 },
			"faces": {
				"down": { "uv": [ 10, 6.7, 11, 6 ], "texture": "#particle" },
				"up": { "uv": [ 10, 6.7, 11, 6 ], "texture": "#particle" },
				"north": { "uv": [ 10, 6.7, 11, 6 ], "texture": "#particle", "rotation": 180 },
				"south": { "uv": [ 10, 6.7, 11, 6 ], "texture": "#particle", "rotation": 180 },
				"west": { "uv": [ 10, 6.7, 11, 6 ], "texture": "#particle", "rotation": 180 },
				"east": { "uv": [ 10, 6.7, 11, 6 ], "texture": "#particle", "rotation": 180 }
			}
		},
		{
			"__comment": "Element",
			"from": [ 13.9635, 3.133, 15.8493 ],
			"to": [ 15.29675, 4.46625, 17.18255 ],
			"rotation": { "origin": [ 15.03604, 3.11851, 16.46898 ], "axis": "z", "angle": -22.5 },
			"faces": {
				"down": { "uv": [ 10, 6.7, 11, 6 ], "texture": "#particle" },
				"up": { "uv": [ 10, 6.7, 11, 6 ], "texture": "#particle" },
				"north": { "uv": [ 10, 6.7, 11, 6 ], "texture": "#particle", "rotation": 180 },
				"south": { "uv": [ 10, 6.7, 11, 6 ], "texture": "#particle", "rotation": 180 },
				"west": { "uv": [ 10, 6.7, 11, 6 ], "texture": "#particle", "rotation": 180 },
				"east": { "uv": [ 10, 6.7, 11, 6 ], "texture": "#particle", "rotation": 180 }
			}
		},
		{
			"__comment": "Element",
			"from": [ -2.9142, 0.7008, 4.9425 ],
			"to": [ 1.2858, 1.9608, 9.5625 ],
			"faces": {
				"down": { "uv": [ 10, 6.7, 11, 6 ], "texture": "#particle", "rotation": 180 },
				"up": { "uv": [ 10, 6.7, 11, 6 ], "texture": "#particle", "rotation": 180 },
				"north": { "uv": [ 10, 6.7, 11, 6 ], "texture": "#particle", "rotation": 180 },
				"south": { "uv": [ 10, 6.7, 11, 6 ], "texture": "#particle", "rotation": 180 },
				"west": { "uv": [ 10, 6.7, 11, 6 ], "texture": "#particle", "rotation": 180 },
				"east": { "uv": [ 10, 6.7, 11, 6 ], "texture": "#particle", "rotation": 180 }
			}
		},
		{
			"__comment": "Element",
			"from": [ 6.0545, 0.7008, 4.1925 ],
			"to": [ 11.30137, 1.9608, 10.45312 ],
			"faces": {
				"down": { "uv": [ 10, 6.7, 11, 6 ], "texture": "#particle", "rotation": 180 },
				"up": { "uv": [ 10, 6.7, 11, 6 ], "texture": "#particle", "rotation": 180 },
				"north": { "uv": [ 10, 6.7, 11, 6 ], "texture": "#particle", "rotation": 180 },
				"south": { "uv": [ 10, 6.7, 11, 6 ], "texture": "#particle", "rotation": 180 },
				"west": { "uv": [ 10, 6.7, 11, 6 ], "texture": "#particle", "rotation": 180 },
				"east": { "uv": [ 10, 6.7, 11, 6 ], "texture": "#particle", "rotation": 180 }
			}
		},
		{
			"__comment": "Element",
			"from": [ 15.6503, 0.3927, 2.2169 ],
			"to": [ 18.2543, 1.1739, 5.0813 ],
			"faces": {
				"down": { "uv": [ 10, 6.7, 11, 6 ], "texture": "#particle" },
				"up": { "uv": [ 10, 6.7, 11, 6 ], "texture": "#particle" },
				"north": { "uv": [ 10, 6.7, 11, 6 ], "texture": "#particle", "rotation": 180 },
				"south": { "uv": [ 10, 6.7, 11, 6 ], "texture": "#particle", "rotation": 180 },
				"west": { "uv": [ 10, 6.7, 11, 6 ], "texture": "#particle", "rotation": 180 },
				"east": { "uv": [ 10, 6.7, 11, 6 ], "texture": "#particle", "rotation": 180 }
			}
		},
		{
			"__comment": "Element",
			"from": [ 14.1991, 0.324, 15.5576 ],
			"to": [ 15.86566, 0.82397, 17.39082 ],
			"faces": {
				"down": { "uv": [ 10, 6.7, 11, 6 ], "texture": "#particle" },
				"up": { "uv": [ 10, 6.7, 11, 6 ], "texture": "#particle" },
				"north": { "uv": [ 10, 6.7, 11, 6 ], "texture": "#particle", "rotation": 180 },
				"south": { "uv": [ 10, 6.7, 11, 6 ], "texture": "#particle", "rotation": 180 },
				"west": { "uv": [ 10, 6.7, 11, 6 ], "texture": "#particle", "rotation": 180 },
				"east": { "uv": [ 10, 6.7, 11, 6 ], "texture": "#particle", "rotation": 180 }
			}
		}
	],
	"display": {
		"gui": {
			"rotation":  [ 0, -153.5, -0.5 ],
			"translation":  [ -0.75, 0.5, 0 ],
			"scale":  [ 0.34, 0.34, 0.34 ]
		},
		"head": {
			"translation":  [ 3.4782, 23.054, 0 ],
			"scale":  [ 2.75, 2.75, 2.75 ]
		},
		"fixed": {
			"rotation":  [ -90, -34, 0 ],
			"translation":  [ 0, 0, -13.91 ],
			"scale":  [ 2, 2, 2 ]
		}
	}
}