{
	"credit": "Made by Regorty",
	"textures": {
		"0": "block/gray_wool",
		"1": "block/yellow_wool",
		"2": "item/custom/varrock/clutter/varrock_mahogany_chair_back_top",
		"particle": "block/gray_wool"
	},
	"elements": [
		{
			"from": [-4, 2, 0],
			"to": [20, 3, 16],
			"rotation": {"angle": 0, "axis": "y", "origin": [-4, 1, 0]},
			"faces": {
				"north": {"uv": [0, 0, 16, 1], "texture": "#1"},
				"east": {"uv": [0, 0, 16, 1], "texture": "#1"},
				"south": {"uv": [0, 0, 16, 1], "texture": "#1"},
				"west": {"uv": [0, 0, 16, 1], "texture": "#1"},
				"down": {"uv": [0, 0, 16, 16], "texture": "#1"}
			}
		},
		{
			"from": [-4, 3, 0],
			"to": [20, 8, 16],
			"rotation": {"angle": 0, "axis": "y", "origin": [-4, 2, 0]},
			"faces": {
				"north": {"uv": [0, 0, 16, 6], "texture": "#0"},
				"east": {"uv": [0, 0, 16, 6], "texture": "#0"},
				"south": {"uv": [0, 0, 16, 6], "texture": "#0"},
				"west": {"uv": [0, 0, 16, 6], "texture": "#0"},
				"up": {"uv": [0, 0, 16, 16], "texture": "#0"}
			}
		},
		{
			"from": [-3, 0, 3],
			"to": [-1, 1, 13],
			"rotation": {"angle": 0, "axis": "y", "origin": [-3, 0, 0]},
			"faces": {
				"north": {"uv": [5.45614, 14.42105, 5.92982, 15.17544], "texture": "#2"},
				"east": {"uv": [7.15789, 14.17544, 8.15789, 15.17544], "texture": "#2"},
				"south": {"uv": [5.45614, 14.42105, 5.92982, 15.17544], "texture": "#2"},
				"west": {"uv": [7.15789, 14.17544, 8.15789, 15.17544], "texture": "#2"},
				"up": {"uv": [5.45614, 14.42105, 5.92982, 15.17544], "texture": "#2"},
				"down": {"uv": [7.15789, 14.17544, 8.15789, 15.17544], "texture": "#2"}
			}
		},
		{
			"from": [-3, 1, 4],
			"to": [-1, 2, 12],
			"rotation": {"angle": 0, "axis": "y", "origin": [-3, 0, 0]},
			"faces": {
				"east": {"uv": [7.15789, 14.17544, 8.15789, 15.17544], "texture": "#2"},
				"west": {"uv": [7.15789, 14.17544, 8.15789, 15.17544], "texture": "#2"}
			}
		},
		{
			"from": [-3, 0.81074, 2.04852],
			"to": [-1, 2.81074, 2.54852],
			"rotation": {"angle": -22.5, "axis": "x", "origin": [-2, 5.81074, 2.54852]},
			"faces": {
				"north": {"uv": [5.45614, 14.42105, 5.92982, 15.17544], "texture": "#2"},
				"east": {"uv": [7.15789, 14.17544, 8.15789, 15.17544], "texture": "#2"},
				"west": {"uv": [7.15789, 14.17544, 8.15789, 15.17544], "texture": "#2"}
			}
		},
		{
			"from": [-3, 0.81074, 13.45148],
			"to": [-1, 2.81074, 13.95148],
			"rotation": {"angle": 22.5, "axis": "x", "origin": [-2, 5.81074, 13.45148]},
			"faces": {
				"east": {"uv": [7.15789, 14.17544, 8.15789, 15.17544], "texture": "#2"},
				"south": {"uv": [5.45614, 14.42105, 5.92982, 15.17544], "texture": "#2"},
				"west": {"uv": [7.15789, 14.17544, 8.15789, 15.17544], "texture": "#2"}
			}
		},
		{
			"from": [17, 0, 3],
			"to": [19, 1, 13],
			"rotation": {"angle": 0, "axis": "y", "origin": [19, 0, 0]},
			"faces": {
				"north": {"uv": [5.92982, 14.42105, 5.45614, 15.17544], "texture": "#2"},
				"east": {"uv": [8.15789, 14.17544, 7.15789, 15.17544], "texture": "#2"},
				"south": {"uv": [5.92982, 14.42105, 5.45614, 15.17544], "texture": "#2"},
				"west": {"uv": [8.15789, 14.17544, 7.15789, 15.17544], "texture": "#2"},
				"up": {"uv": [5.92982, 14.42105, 5.45614, 15.17544], "texture": "#2"},
				"down": {"uv": [8.15789, 14.17544, 7.15789, 15.17544], "texture": "#2"}
			}
		},
		{
			"from": [17, 0.81074, 13.45148],
			"to": [19, 2.81074, 13.95148],
			"rotation": {"angle": 22.5, "axis": "x", "origin": [18, 5.81074, 13.45148]},
			"faces": {
				"east": {"uv": [8.15789, 14.17544, 7.15789, 15.17544], "texture": "#2"},
				"south": {"uv": [5.92982, 14.42105, 5.45614, 15.17544], "texture": "#2"},
				"west": {"uv": [8.15789, 14.17544, 7.15789, 15.17544], "texture": "#2"}
			}
		},
		{
			"from": [17, 1, 4],
			"to": [19, 2, 12],
			"rotation": {"angle": 0, "axis": "y", "origin": [19, 0, 0]},
			"faces": {
				"east": {"uv": [8.15789, 14.17544, 7.15789, 15.17544], "texture": "#2"},
				"west": {"uv": [8.15789, 14.17544, 7.15789, 15.17544], "texture": "#2"}
			}
		},
		{
			"from": [17, 0.81074, 2.04852],
			"to": [19, 2.81074, 2.54852],
			"rotation": {"angle": -22.5, "axis": "x", "origin": [18, 5.81074, 2.54852]},
			"faces": {
				"north": {"uv": [5.92982, 14.42105, 5.45614, 15.17544], "texture": "#2"},
				"east": {"uv": [8.15789, 14.17544, 7.15789, 15.17544], "texture": "#2"},
				"west": {"uv": [8.15789, 14.17544, 7.15789, 15.17544], "texture": "#2"}
			}
		}
	],
	"display": {
		"thirdperson_righthand": {
			"scale": [0.15, 0.15, 0.15]
		},
		"firstperson_righthand": {
			"scale": [0.15, 0.15, 0.15]
		},
		"gui": {
			"rotation": [12, 25, 0],
			"scale": [0.6, 0.6, 0.6]
		},
		"fixed": {
			"rotation": [-90, 0, 0],
			"translation": [0, 16, 2],
			"scale": [4, 4, 4]
		}
	}
}