{
	"credit": "Made with Blockbench",
	"textures": {
		"0": "item/misc/greggs_door_shield",
		"1": "item/custom/tools/iron",
		"particle": "item/misc/greggs_door_shield"
	},
	"elements": [
		{
			"from": [0, 3.9, 0],
			"to": [1, 18.975, 9.15],
			"faces": {
				"north": {"uv": [12.875, 0, 15.9375, 16], "texture": "#0"},
				"east": {"uv": [0, 0, 15.9375, 16], "texture": "#0"},
				"south": {"uv": [0, 0, 3.0625, 16], "texture": "#0"},
				"west": {"uv": [0, 0, 15.9375, 16], "texture": "#0"},
				"up": {"uv": [6.3125, 0, 9.6875, 1.1875], "texture": "#0"},
				"down": {"uv": [0.125, 0, 16, 1.375], "texture": "#0"}
			}
		},
		{
			"from": [-0.1, 12.325, 6.9],
			"to": [0.9, 13.325, 7.9],
			"faces": {
				"north": {"uv": [0, 0, 16, 16], "texture": "#1"},
				"south": {"uv": [0, 0, 16, 16], "texture": "#1"},
				"west": {"uv": [0, 0, 16, 16], "texture": "#1"},
				"up": {"uv": [0, 0, 16, 16], "texture": "#1"},
				"down": {"uv": [0, 0, 16, 16], "texture": "#1"}
			}
		},
		{
			"from": [0.2, 8.825, 6.8],
			"to": [1.2, 9.825, 7.8],
			"rotation": {"angle": 0, "axis": "y", "origin": [1.1, -3.5, -0.1]},
			"faces": {
				"north": {"uv": [0, 0, 16, 16], "texture": "#1"},
				"east": {"uv": [0, 0, 16, 16], "texture": "#1"},
				"south": {"uv": [0, 0, 16, 16], "texture": "#1"},
				"up": {"uv": [0, 0, 16, 16], "texture": "#1"},
				"down": {"uv": [0, 0, 16, 16], "texture": "#1"}
			}
		},
		{
			"from": [0.2, 8.825, 1.375],
			"to": [1.2, 9.825, 2.375],
			"rotation": {"angle": 0, "axis": "y", "origin": [1.1, -3.5, -5.525]},
			"faces": {
				"north": {"uv": [0, 0, 16, 16], "texture": "#1"},
				"east": {"uv": [0, 0, 16, 16], "texture": "#1"},
				"south": {"uv": [0, 0, 16, 16], "texture": "#1"},
				"up": {"uv": [0, 0, 16, 16], "texture": "#1"},
				"down": {"uv": [0, 0, 16, 16], "texture": "#1"}
			}
		},
		{
			"from": [-0.1, 13.975, 6.9],
			"to": [0.9, 14.975, 7.9],
			"faces": {
				"north": {"uv": [0, 0, 16, 16], "texture": "#1"},
				"south": {"uv": [0, 0, 16, 16], "texture": "#1"},
				"west": {"uv": [0, 0, 16, 16], "texture": "#1"},
				"up": {"uv": [0, 0, 16, 16], "texture": "#1"},
				"down": {"uv": [0, 0, 16, 16], "texture": "#1"}
			}
		},
		{
			"from": [0.2, 10.475, 6.8],
			"to": [1.2, 11.475, 7.8],
			"rotation": {"angle": 0, "axis": "y", "origin": [1.1, -3.5, -0.1]},
			"faces": {
				"north": {"uv": [0, 0, 16, 16], "texture": "#1"},
				"east": {"uv": [0, 0, 16, 16], "texture": "#1"},
				"south": {"uv": [0, 0, 16, 16], "texture": "#1"},
				"up": {"uv": [0, 0, 16, 16], "texture": "#1"},
				"down": {"uv": [0, 0, 16, 16], "texture": "#1"}
			}
		},
		{
			"from": [0.2, 10.475, 1.375],
			"to": [1.2, 11.475, 2.375],
			"rotation": {"angle": 0, "axis": "y", "origin": [1.1, -3.5, -5.525]},
			"faces": {
				"north": {"uv": [0, 0, 16, 16], "texture": "#1"},
				"east": {"uv": [0, 0, 16, 16], "texture": "#1"},
				"south": {"uv": [0, 0, 16, 16], "texture": "#1"},
				"up": {"uv": [0, 0, 16, 16], "texture": "#1"},
				"down": {"uv": [0, 0, 16, 16], "texture": "#1"}
			}
		},
		{
			"from": [-0.545, 14.155, 7.13],
			"to": [-0.005, 14.695, 7.67],
			"rotation": {"angle": 0, "axis": "y", "origin": [4.504, 6.6085, 3.404]},
			"faces": {
				"north": {"uv": [0, 0, 16, 16], "texture": "#1"},
				"south": {"uv": [0, 0, 16, 16], "texture": "#1"},
				"up": {"uv": [0, 0, 16, 16], "texture": "#1"},
				"down": {"uv": [0, 0, 16, 16], "texture": "#1"}
			}
		},
		{
			"from": [1.105, 10.655, 7.03],
			"to": [1.645, 11.195, 7.57],
			"rotation": {"angle": 0, "axis": "y", "origin": [-3.404, 3.1085, 3.304]},
			"faces": {
				"north": {"uv": [0, 0, 16, 16], "texture": "#1"},
				"south": {"uv": [0, 0, 16, 16], "texture": "#1"},
				"up": {"uv": [0, 0, 16, 16], "texture": "#1"},
				"down": {"uv": [0, 0, 16, 16], "texture": "#1"}
			}
		},
		{
			"from": [1.105, 10.655, 1.605],
			"to": [1.645, 11.195, 2.145],
			"rotation": {"angle": 0, "axis": "y", "origin": [-3.404, 3.1085, -2.121]},
			"faces": {
				"north": {"uv": [0, 0, 16, 16], "texture": "#1"},
				"south": {"uv": [0, 0, 16, 16], "texture": "#1"},
				"up": {"uv": [0, 0, 16, 16], "texture": "#1"},
				"down": {"uv": [0, 0, 16, 16], "texture": "#1"}
			}
		},
		{
			"from": [-0.545, 12.54206, 7.13],
			"to": [-0.005, 13.08206, 7.67],
			"rotation": {"angle": 0, "axis": "y", "origin": [4.504, 20.62856, 3.404]},
			"faces": {
				"north": {"uv": [0, 0, 16, 16], "texture": "#1"},
				"south": {"uv": [0, 0, 16, 16], "texture": "#1"},
				"up": {"uv": [0, 0, 16, 16], "texture": "#1"},
				"down": {"uv": [0, 0, 16, 16], "texture": "#1"}
			}
		},
		{
			"from": [1.105, 9.04206, 7.03],
			"to": [1.645, 9.58206, 7.57],
			"rotation": {"angle": 0, "axis": "y", "origin": [-3.404, 17.12856, 3.304]},
			"faces": {
				"north": {"uv": [0, 0, 16, 16], "texture": "#1"},
				"south": {"uv": [0, 0, 16, 16], "texture": "#1"},
				"up": {"uv": [0, 0, 16, 16], "texture": "#1"},
				"down": {"uv": [0, 0, 16, 16], "texture": "#1"}
			}
		},
		{
			"from": [1.105, 9.04206, 1.605],
			"to": [1.645, 9.58206, 2.145],
			"rotation": {"angle": 0, "axis": "y", "origin": [-3.404, 17.12856, -2.121]},
			"faces": {
				"north": {"uv": [0, 0, 16, 16], "texture": "#1"},
				"south": {"uv": [0, 0, 16, 16], "texture": "#1"},
				"up": {"uv": [0, 0, 16, 16], "texture": "#1"},
				"down": {"uv": [0, 0, 16, 16], "texture": "#1"}
			}
		},
		{
			"from": [-1.115, 14.04316, 7.13],
			"to": [-0.275, 14.58316, 7.67],
			"rotation": {"angle": 45, "axis": "z", "origin": [-0.545, 14.31316, 7.4]},
			"faces": {
				"north": {"uv": [0, 0, 16, 16], "texture": "#1"},
				"south": {"uv": [0, 0, 16, 16], "texture": "#1"},
				"up": {"uv": [0, 0, 16, 16], "texture": "#1"},
				"down": {"uv": [0, 0, 16, 16], "texture": "#1"}
			}
		},
		{
			"from": [1.375, 10.54316, 7.03],
			"to": [2.215, 11.08316, 7.57],
			"rotation": {"angle": -45, "axis": "z", "origin": [1.645, 10.81316, 7.3]},
			"faces": {
				"north": {"uv": [0, 0, 16, 16], "texture": "#1"},
				"south": {"uv": [0, 0, 16, 16], "texture": "#1"},
				"up": {"uv": [0, 0, 16, 16], "texture": "#1"},
				"down": {"uv": [0, 0, 16, 16], "texture": "#1"}
			}
		},
		{
			"from": [1.375, 10.54316, 1.605],
			"to": [2.215, 11.08316, 2.145],
			"rotation": {"angle": -45, "axis": "z", "origin": [1.645, 10.81316, 1.875]},
			"faces": {
				"north": {"uv": [0, 0, 16, 16], "texture": "#1"},
				"south": {"uv": [0, 0, 16, 16], "texture": "#1"},
				"up": {"uv": [0, 0, 16, 16], "texture": "#1"},
				"down": {"uv": [0, 0, 16, 16], "texture": "#1"}
			}
		},
		{
			"from": [-1.115, 12.6539, 7.13],
			"to": [-0.275, 13.1939, 7.67],
			"rotation": {"angle": -45, "axis": "z", "origin": [-0.545, 12.9239, 7.4]},
			"faces": {
				"north": {"uv": [0, 0, 16, 16], "texture": "#1"},
				"south": {"uv": [0, 0, 16, 16], "texture": "#1"},
				"up": {"uv": [0, 0, 16, 16], "texture": "#1"},
				"down": {"uv": [0, 0, 16, 16], "texture": "#1"}
			}
		},
		{
			"from": [1.375, 9.1539, 7.03],
			"to": [2.215, 9.6939, 7.57],
			"rotation": {"angle": 45, "axis": "z", "origin": [1.645, 9.4239, 7.3]},
			"faces": {
				"north": {"uv": [0, 0, 16, 16], "texture": "#1"},
				"south": {"uv": [0, 0, 16, 16], "texture": "#1"},
				"up": {"uv": [0, 0, 16, 16], "texture": "#1"},
				"down": {"uv": [0, 0, 16, 16], "texture": "#1"}
			}
		},
		{
			"from": [1.375, 9.1539, 1.605],
			"to": [2.215, 9.6939, 2.145],
			"rotation": {"angle": 45, "axis": "z", "origin": [1.645, 9.4239, 1.875]},
			"faces": {
				"north": {"uv": [0, 0, 16, 16], "texture": "#1"},
				"south": {"uv": [0, 0, 16, 16], "texture": "#1"},
				"up": {"uv": [0, 0, 16, 16], "texture": "#1"},
				"down": {"uv": [0, 0, 16, 16], "texture": "#1"}
			}
		},
		{
			"from": [-1.13897, 13.13603, 7.13],
			"to": [-0.59897, 14.10103, 7.67],
			"rotation": {"angle": 0, "axis": "z", "origin": [-0.81305, 13.27103, 7.4]},
			"faces": {
				"north": {"uv": [0, 0, 16, 16], "rotation": 270, "texture": "#1"},
				"east": {"uv": [0, 0, 16, 16], "rotation": 270, "texture": "#1"},
				"south": {"uv": [0, 0, 16, 16], "rotation": 270, "texture": "#1"},
				"west": {"uv": [0, 0, 16, 16], "rotation": 270, "texture": "#1"}
			}
		},
		{
			"from": [1.69897, 9.63603, 7.03],
			"to": [2.23897, 10.60103, 7.57],
			"rotation": {"angle": 0, "axis": "z", "origin": [1.91305, 9.77103, 7.3]},
			"faces": {
				"north": {"uv": [0, 0, 16, 16], "rotation": 270, "texture": "#1"},
				"east": {"uv": [0, 0, 16, 16], "rotation": 270, "texture": "#1"},
				"south": {"uv": [0, 0, 16, 16], "rotation": 270, "texture": "#1"},
				"west": {"uv": [0, 0, 16, 16], "rotation": 270, "texture": "#1"}
			}
		},
		{
			"from": [1.69897, 9.63603, 1.605],
			"to": [2.23897, 10.60103, 2.145],
			"rotation": {"angle": 0, "axis": "z", "origin": [1.91305, 9.77103, 1.875]},
			"faces": {
				"north": {"uv": [0, 0, 16, 16], "rotation": 270, "texture": "#1"},
				"east": {"uv": [0, 0, 16, 16], "rotation": 270, "texture": "#1"},
				"south": {"uv": [0, 0, 16, 16], "rotation": 270, "texture": "#1"},
				"west": {"uv": [0, 0, 16, 16], "rotation": 270, "texture": "#1"}
			}
		}
	],
	"display": {
		"thirdperson_righthand": {
			"rotation": [70, -91, 0],
			"translation": [-12.75, -14.25, 1.25],
			"scale": [2.0703, 2.4609, 1.94141]
		},
		"thirdperson_lefthand": {
			"rotation": [69, 90, 0],
			"translation": [0.75, -13.25, 1.5],
			"scale": [2.07032, 2.46094, 1.94141]
		},
		"firstperson_righthand": {
			"rotation": [-6, -90, -5],
			"translation": [-23, -18, 16],
			"scale": [4, 4, 4]
		},
		"firstperson_lefthand": {
			"rotation": [0, 72, 12],
			"translation": [9.75, -24, 3.75],
			"scale": [2.09766, 2.09766, 2.09766]
		},
		"gui": {
			"rotation": [22, 56, -38],
			"translation": [4.25, -5.5, 0],
			"scale": [0.90234, 0.90234, 0.90234]
		},
		"head": {
			"rotation": [0, 90, 0],
			"translation": [6.75, 6, -8.75],
			"scale": [2.02148, 2.02148, 2.02148]
		},
		"fixed": {
			"rotation": [0, -90, 0],
			"translation": [-12, 8.5, 29],
			"scale": [4, 3.05078, 3.53906]
		}
	}
}